Workbook

Sheet metas
A1: PAINEL DE INDICADORES | C1: Meta | E1: Realizado | F1: Próxima
A2: NÚCLEO DE GESTÃO | B2: NÚCLEO DE GESTÃO PARTICIPATIVA
A3: 6. CBH – Reunião Ordinária do Comitê | B3: Reunião Ordinária | C3: 160
B4: Ordinária 1 | C4: 40 | D4: =IFERROR(__xludf.DUMMYFUNCTION("FILTER(gest!B:C,(gest!A:A=A3)*(YEAR(gest!B:B)=YEAR(TODAY())))"),46079.0) -> 46079 | E4: =IFERROR(__xludf.DUMMYFUNCTION("""COMPUTED_VALUE"""),"34") -> 34 | F4: =IF(AND(ISBLANK(E4),NOT(ISBLANK(D4))),D4,"")
B5: Ordinária 2 | C5: 40 | D5: =IFERROR(__xludf.DUMMYFUNCTION("""COMPUTED_VALUE"""),46198.0) -> 46198 | F5: =IF(AND(ISBLANK(E5),NOT(ISBLANK(D5))),D5,"") -> 46198
B6: Ordinária 3 | C6: 40 | F6: =IF(AND(ISBLANK(E6),NOT(ISBLANK(D6))),D6,"")
B7: Ordinária 4 | C7: 40 | F7: =IF(AND(ISBLANK(E7),NOT(ISBLANK(D7))),D7,"")
A8: 7. CBH – Reunião Extraordinária do Comitê | B8: Reunião Extraordinária | C8: 160
B9: Extraordinária 1 | C9: 40 | D9: =IFERROR(__xludf.DUMMYFUNCTION("FILTER(gest!B:C,(gest!A:A=A8)*(YEAR(gest!B:B)=YEAR(TODAY())))"),46176.0) -> 46176 | E9: =IFERROR(__xludf.DUMMYFUNCTION("""COMPUTED_VALUE"""),"28") -> 28 | F9: =IF(AND(ISBLANK(E9),NOT(ISBLANK(D9))),D9,"")
B10: Extraordinária 2 | C10: 40 | F10: =IF(AND(ISBLANK(E10),NOT(ISBLANK(D10))),D10,"")
B11: Extraordinária 3 | C11: 40 | F11: =IF(AND(ISBLANK(E11),NOT(ISBLANK(D11))),D11,"")
B12: Extraordinária 4 | C12: 40 | F12: =IF(AND(ISBLANK(E12),NOT(ISBLANK(D12))),D12,"")
B13: Extraordinária 5 | C13: 40 | F13: =IF(AND(ISBLANK(E13),NOT(ISBLANK(D13))),D13,"")
A14: 12. CBH – Reunião do Fórum Cearense de Comitê | B14: Reunião do Fórum Cearense de Comitê | C14: 4 | E14: =COUNTA(E15:E18) -> 1
B15: FCCH 1 | D15: =IFERROR(__xludf.DUMMYFUNCTION("FILTER(gest!B:C,(gest!A:A=A14)*(YEAR(gest!B:B)=YEAR(TODAY())))"),46063.0) -> 46063 | E15: =IFERROR(__xludf.DUMMYFUNCTION("""COMPUTED_VALUE"""),"1") -> 1 | F15: =IF(AND(ISBLANK(E15),NOT(ISBLANK(D15))),D15,"")
B16: FCCH 2 | D16: =IFERROR(__xludf.DUMMYFUNCTION("""COMPUTED_VALUE"""),46189.0) -> 46189 | F16: =IF(AND(ISBLANK(E16),NOT(ISBLANK(D16))),D16,"") -> 46189
B17: FCCH 3 | F17: =IF(AND(ISBLANK(E17),NOT(ISBLANK(D17))),D17,"")
B18: FCCH 4 | F18: =IF(AND(ISBLANK(E18),NOT(ISBLANK(D18))),D18,"")
A19: 16. CG – Capacitação da Comissão Gestora | B19: Capacitação da Comissão Gestora | C19: 8 | E19: =COUNTIFS(gest!A:A,A19,gest!B:B,">="&DATE(YEAR(TODAY()),1,1),gest!B:B,"<="&TODAY()) -> 2
D20: =IFERROR(__xludf.DUMMYFUNCTION("FILTER(gest!B:C,(gest!A:A=A19)*(YEAR(gest!B:B)=YEAR(TODAY())))"),46087.0) -> 46087 | E20: =IFERROR(__xludf.DUMMYFUNCTION("""COMPUTED_VALUE"""),"8") -> 8
D21: =IFERROR(__xludf.DUMMYFUNCTION("""COMPUTED_VALUE"""),46090.0) -> 46090 | E21: =IFERROR(__xludf.DUMMYFUNCTION("""COMPUTED_VALUE"""),"6") -> 6
A29: 1. Alocação de água – Reunião de Alocação Participativa | B29: Alocação participativa | C29: 8 | E29: =COUNTIFS(gest!A:A,A29,gest!B:B,">="&DATE(YEAR(TODAY()),1,1),gest!B:B,"<="&TODAY()) -> 0
D30: =IFERROR(__xludf.DUMMYFUNCTION("FILTER(gest!B:C,(gest!A:A=A29)*(YEAR(gest!B:B)=YEAR(TODAY())))"),46203.0) -> 46203
D31: =IFERROR(__xludf.DUMMYFUNCTION("""COMPUTED_VALUE"""),46203.0) -> 46203
A39: 2. Alocação de água – Reunião de Acompanhamento da Operação | B39: Acompanhamento da Operação | C39: 8 | E39: =COUNTIFS(gest!A:A,A39,gest!B:B,">="&DATE(YEAR(TODAY()),1,1),gest!B:B,"<="&TODAY()) -> 0
D40: =IFERROR(__xludf.DUMMYFUNCTION("FILTER(gest!B:C,(gest!A:A=A39)*(YEAR(gest!B:B)=YEAR(TODAY())))"),"#N/A") -> #N/A
A49: 3. Alocação de água – Reunião de Avaliação da Operação | B49: Avaliação da Operação | C49: 8 | E49: =COUNTIFS(gest!A:A,A49,gest!B:B,">="&DATE(YEAR(TODAY()),1,1),gest!B:B,"<="&TODAY()) -> 10
D50: =IFERROR(__xludf.DUMMYFUNCTION("FILTER(gest!B:C,(gest!A:A=A49)*(YEAR(gest!B:B)=YEAR(TODAY())))"),46083.0) -> 46083 | E50: =IFERROR(__xludf.DUMMYFUNCTION("""COMPUTED_VALUE"""),"0") -> 0
D51: =IFERROR(__xludf.DUMMYFUNCTION("""COMPUTED_VALUE"""),46084.0) -> 46084
D52: =IFERROR(__xludf.DUMMYFUNCTION("""COMPUTED_VALUE"""),46085.0) -> 46085 | E52: =IFERROR(__xludf.DUMMYFUNCTION("""COMPUTED_VALUE"""),"5") -> 5
D53: =IFERROR(__xludf.DUMMYFUNCTION("""COMPUTED_VALUE"""),46086.0) -> 46086 | E53: =IFERROR(__xludf.DUMMYFUNCTION("""COMPUTED_VALUE"""),"10") -> 10
D54: =IFERROR(__xludf.DUMMYFUNCTION("""COMPUTED_VALUE"""),46087.0) -> 46087 | E54: =IFERROR(__xludf.DUMMYFUNCTION("""COMPUTED_VALUE"""),"8") -> 8
D55: =IFERROR(__xludf.DUMMYFUNCTION("""COMPUTED_VALUE"""),46090.0) -> 46090 | E55: =IFERROR(__xludf.DUMMYFUNCTION("""COMPUTED_VALUE"""),"5") -> 5
D56: =IFERROR(__xludf.DUMMYFUNCTION("""COMPUTED_VALUE"""),46091.0) -> 46091
D57: =IFERROR(__xludf.DUMMYFUNCTION("""COMPUTED_VALUE"""),46092.0) -> 46092 | E57: =IFERROR(__xludf.DUMMYFUNCTION("""COMPUTED_VALUE"""),"10") -> 10
D58: =IFERROR(__xludf.DUMMYFUNCTION("""COMPUTED_VALUE"""),46093.0) -> 46093
D59: =IFERROR(__xludf.DUMMYFUNCTION("""COMPUTED_VALUE"""),46093.0) -> 46093
A61: NÚCLEO DE OPERAÇÃO | B61: NÚCLEO DE OPERAÇÃO
A62: INDICADOR 1: CORREÇÃO DAS ANOMALIAS DE RESPONSABILIDADE DAS REGIONAIS (R) E DOS AGIRS (A) DAS BARRAGENS ESTADUAIS MONITORADAS PELA COGERH | B62: Anomalias Corrigidas | C62: 23 | E62: =SUM(E63:E64) -> 15
A63: Objetivos: Promover a Operação a Manutenção e a Segurança da Infraestrutura Hídrica da Companhia | B63: Anomalias - Regional | C63: 10 | E63: =IFERROR(__xludf.DUMMYFUNCTION("IMPORTRANGE(""https://docs.google.com/spreadsheets/d/1qH75nopdqebmsXi99R6n0ZSfkSWO3wqoz2qnUvKnI0w/edit?gid=1285399262#gid=1285399262"",""res!c6:c7"")"),6.0) -> 6
B64: Anomalias - Agirs | C64: 13 | E64: =IFERROR(__xludf.DUMMYFUNCTION("""COMPUTED_VALUE"""),9.0) -> 9
A66: INDICADOR 2: ÍNDICE DE REGULARIZAÇÃO DE COBRANÇA | B66: Regularização da Cobrança | C66: 37 | E66: =SUM(E67:E68) -> 28
A67: Objetivos: Expandir e Diversificar a Receita; Ampliar a Regularização do Uso dos Recursos Hídricos | B67: Regularização Novos usuários | C67: 19 | E67: 12
B68: Regularização Inadimplentes | C68: 18 | E68: 16
A70: INDICADOR 3: FISCALIZAÇÃO | B70: Fiscalização | C70: 105 | E70: =SUM(E71:E72) -> 51
A71: Objetivos: Ampliar a regularização do uso dos recursos hídricos | B71: Com RV | C71: 75 | E71: =SUM(oper!C3:N3) -> 13
B72: Sem RV | C72: 30 | E72: =SUM(oper!C2:N2) -> 38
A74: INDICADOR 4: INSTALACÃO E MANUTENÇÃO DE MEDIDORES | B74: Instalação e Manutenção de medidores | C74: 0.43 | E74: =oper!F8 -> 0.11
A75: Objetivos: Ampliar a regularização do uso dos recursos hídricos | B75: Manutenções | C75: 18 | E75: =oper!D8 -> 4
B76: Instalações | C76: 10 | E76: =oper!E8 -> 3
B77: Medições | C77: 56 | E77: =oper!C8 -> 11
A79: INDICADOR 5: QUANTIDADE DE BATIMETRIAS REALIZADAS (0 DE 2) | B79: Batrimetrias | C79: 2 | E79: 1
A85: PROGRAMAÇÃO DE HOJE
A86: =IFERROR(__xludf.DUMMYFUNCTION("FILTER(prog!E:E,INT(prog!A:A)=TODAY())"),"Solicitar apoio logístico para Erandir - reunião do FCCBH (PROCOMITÊ)") -> Solicitar apoio logístico para Erandir - reunião do FCCBH (PROCOMITÊ)
A87: =IFERROR(__xludf.DUMMYFUNCTION("""COMPUTED_VALUE"""),"Publicação de aniversário de Raimundo Ribeiro Sales") -> Publicação de aniversário de Raimundo Ribeiro Sales
A88: =IFERROR(__xludf.DUMMYFUNCTION("""COMPUTED_VALUE"""),"Mobilização para 75ª Reunião Ordinária (Morrinhos/Santana do Acaraú/Amontada)") -> Mobilização para 75ª Reunião Ordinária (Morrinhos/Santana do Acaraú/Amontada)
A89: =IFERROR(__xludf.DUMMYFUNCTION("""COMPUTED_VALUE"""),"Providenciar atividades programadas para o mês de julho") -> Providenciar atividades programadas para o mês de julho
A90: =IFERROR(__xludf.DUMMYFUNCTION("""COMPUTED_VALUE"""),"Inspeção de Segurança e Medição de Vazão (Patos e Santo Antonio de Aracatiaçu)") -> Inspeção de Segurança e Medição de Vazão (Patos e Santo Antonio de Aracatiaçu)
A99: AÇUDES | B99: hm³ | C99: %
A100: ='açudes'!A1 -> GAMELEIRA | B100: ='açudes'!I1 -> 27.86 | C100: ='açudes'!J1 -> 99.78
A101: ='açudes'!A2 -> MISSI | B101: ='açudes'!I2 -> 54.37 | C101: ='açudes'!J2 -> 100
A102: ='açudes'!A3 -> POÇO VERDE | B102: ='açudes'!I3 -> 13.34 | C102: ='açudes'!J3 -> 100
A103: ='açudes'!A4 -> MUNDAÚ | B103: ='açudes'!I4 -> 21.3 | C103: ='açudes'!J4 -> 100
A104: ='açudes'!A5 -> QUANDÚ | B104: ='açudes'!I5 -> 2.45 | C104: ='açudes'!J5 -> 100
A105: ='açudes'!A6 -> S. PEDRO TIMBAÚBA | B105: ='açudes'!I6 -> 15.77 | C105: ='açudes'!J6 -> 100
A106: ='açudes'!A7 -> STO. ANTÔNIO DE ARACATIAÇU | B106: ='açudes'!I7 -> 26.88 | C106: ='açudes'!J7 -> 93.74
A107: ='açudes'!A8 -> PATOS | B107: ='açudes'!I8 -> 6.87 | C107: ='açudes'!J8 -> 90.94
A108: ='açudes'!A9

Sheet açudes
A1: =IFERROR(__xludf.DUMMYFUNCTION("IMPORTRANGE(""https://docs.google.com/spreadsheets/d/1U7xw4reZguSls-dnmJ8PgEtHEv2QU44KRoJGWbCA3sY/edit?gid=2350551#gid=2350551"", ""APORTES!C7:L14"")"),"GAMELEIRA") -> GAMELEIRA | B1: =IFERROR(__xludf.DUMMYFUNCTION("""COMPUTED_VALUE"""),"Itapipoca") -> Itapipoca | C1: =IFERROR(__xludf.DUMMYFUNCTION("""COMPUTED_VALUE"""),36.98) -> 36.98 | D1: =IFERROR(__xludf.DUMMYFUNCTION("""COMPUTED_VALUE"""),36.99) -> 36.99 | E1: =IFERROR(__xludf.DUMMYFUNCTION("""COMPUTED_VALUE"""),62759.0) -> 62759 | F1: =IFERROR(__xludf.DUMMYFUNCTION("""COMPUTED_VALUE"""),0.01) -> 0.01 | G1: =IFERROR(__xludf.DUMMYFUNCTION("""COMPUTED_VALUE"""),0.00224766633470441) -> 0.0022476663 | H1: =IFERROR(__xludf.DUMMYFUNCTION("""COMPUTED_VALUE"""),"#REF!") -> #REF! | I1: =IFERROR(__xludf.DUMMYFUNCTION("""COMPUTED_VALUE"""),27.86) -> 27.86 | J1: =IFERROR(__xludf.DUMMYFUNCTION("""COMPUTED_VALUE"""),99.78) -> 99.78
A2: =IFERROR(__xludf.DUMMYFUNCTION("""COMPUTED_VALUE"""),"MISSI") -> MISSI | B2: =IFERROR(__xludf.DUMMYFUNCTION("""COMPUTED_VALUE"""),"Miraíma") -> Miraíma | C2: =IFERROR(__xludf.DUMMYFUNCTION("""COMPUTED_VALUE"""),54.720000000000006) -> 54.72 | D2: =IFERROR(__xludf.DUMMYFUNCTION("""COMPUTED_VALUE"""),54.71) -> 54.71 | E2: =IFERROR(__xludf.DUMMYFUNCTION("""COMPUTED_VALUE"""),0.0) -> 0 | F2: =IFERROR(__xludf.DUMMYFUNCTION("""COMPUTED_VALUE"""),-0.01) -> -0.01 | G2: =IFERROR(__xludf.DUMMYFUNCTION("""COMPUTED_VALUE"""),0.0) -> 0 | H2: =IFERROR(__xludf.DUMMYFUNCTION("""COMPUTED_VALUE"""),"#REF!") -> #REF! | I2: =IFERROR(__xludf.DUMMYFUNCTION("""COMPUTED_VALUE"""),54.37) -> 54.37 | J2: =IFERROR(__xludf.DUMMYFUNCTION("""COMPUTED_VALUE"""),100.0) -> 100
A3: =IFERROR(__xludf.DUMMYFUNCTION("""COMPUTED_VALUE"""),"POÇO VERDE") -> POÇO VERDE | B3: =IFERROR(__xludf.DUMMYFUNCTION("""COMPUTED_VALUE"""),"Itapipoca") -> Itapipoca | C3: =IFERROR(__xludf.DUMMYFUNCTION("""COMPUTED_VALUE"""),68.09000000000006) -> 68.09 | D3: =IFERROR(__xludf.DUMMYFUNCTION("""COMPUTED_VALUE"""),68.09000000000006) -> 68.09 | E3: =IFERROR(__xludf.DUMMYFUNCTION("""COMPUTED_VALUE"""),0.0) -> 0 | F3: =IFERROR(__xludf.DUMMYFUNCTION("""COMPUTED_VALUE"""),0.0) -> 0 | G3: =IFERROR(__xludf.DUMMYFUNCTION("""COMPUTED_VALUE"""),0.0) -> 0 | H3: =IFERROR(__xludf.DUMMYFUNCTION("""COMPUTED_VALUE"""),"") | I3: =IFERROR(__xludf.DUMMYFUNCTION("""COMPUTED_VALUE"""),13.34) -> 13.34 | J3: =IFERROR(__xludf.DUMMYFUNCTION("""COMPUTED_VALUE"""),100.0) -> 100
A4: =IFERROR(__xludf.DUMMYFUNCTION("""COMPUTED_VALUE"""),"MUNDAÚ") -> MUNDAÚ | B4: =IFERROR(__xludf.DUMMYFUNCTION("""COMPUTED_VALUE"""),"Uruburetama") -> Uruburetama | C4: =IFERROR(__xludf.DUMMYFUNCTION("""COMPUTED_VALUE"""),166.49) -> 166.49 | D4: =IFERROR(__xludf.DUMMYFUNCTION("""COMPUTED_VALUE"""),166.48) -> 166.48 | E4: =IFERROR(__xludf.DUMMYFUNCTION("""COMPUTED_VALUE"""),0.0) -> 0 | F4: =IFERROR(__xludf.DUMMYFUNCTION("""COMPUTED_VALUE"""),-0.01) -> -0.01 | G4: =IFERROR(__xludf.DUMMYFUNCTION("""COMPUTED_VALUE"""),0.0) -> 0 | H4: =IFERROR(__xludf.DUMMYFUNCTION("""COMPUTED_VALUE"""),"#REF!") -> #REF! | I4: =IFERROR(__xludf.DUMMYFUNCTION("""COMPUTED_VALUE"""),21.3) -> 21.3 | J4: =IFERROR(__xludf.DUMMYFUNCTION("""COMPUTED_VALUE"""),100.0) -> 100
A5: =IFERROR(__xludf.DUMMYFUNCTION("""COMPUTED_VALUE"""),"QUANDÚ") -> QUANDÚ | B5: =IFERROR(__xludf.DUMMYFUNCTION("""COMPUTED_VALUE"""),"Itapipoca") -> Itapipoca | C5: =IFERROR(__xludf.DUMMYFUNCTION("""COMPUTED_VALUE"""),98.52) -> 98.52 | D5: =IFERROR(__xludf.DUMMYFUNCTION("""COMPUTED_VALUE"""),98.52) -> 98.52 | E5: =IFERROR(__xludf.DUMMYFUNCTION("""COMPUTED_VALUE"""),0.0) -> 0 | F5: =IFERROR(__xludf.DUMMYFUNCTION("""COMPUTED_VALUE"""),0.0) -> 0 | G5: =IFERROR(__xludf.DUMMYFUNCTION("""COMPUTED_VALUE"""),0.0) -> 0 | H5: =IFERROR(__xludf.DUMMYFUNCTION("""COMPUTED_VALUE"""),"") | I5: =IFERROR(__xludf.DUMMYFUNCTION("""COMPUTED_VALUE"""),2.45) -> 2.45 | J5: =IFERROR(__xludf.DUMMYFUNCTION("""COMPUTED_VALUE"""),100.0) -> 100
A6: =IFERROR(__xludf.DUMMYFUNCTION("""COMPUTED_VALUE"""),"S. PEDRO TIMBAÚBA") -> S. PEDRO TIMBAÚBA | B6: =IFERROR(__xludf.DUMMYFUNCTION("""COMPUTED_VALUE"""),"Miraíma") -> Miraíma | C6: =IFERROR(__xludf.DUMMYFUNCTION("""COMPUTED_VALUE"""),99.05) -> 99.05 | D6: =IFERROR(__xludf.DUMMYFUNCTION("""COMPUTED_VALUE"""),99.04) -> 99.04 | E6: =IFERROR(__xludf.DUMMYFUNCTION("""COMPUTED_VALUE"""),0.0) -> 0 | F6: =IFERROR(__xludf.DUMMYFUNCTION("""COMPUTED_VALUE"""),-0.01) -> -0.01 | G6: =IFERROR(__xludf.DUMMYFUNCTION("""COMPUTED_VALUE"""),0.0) -> 0 | H6: =IFERROR(__xludf.DUMMYFUNCTION("""COMPUTED_VALUE"""),"#REF!") -> #REF! | I6: =IFERROR(__xludf.DUMMYFUNCTION("""COMPUTED_VALUE"""),15.77) -> 15.77 | J6: =IFERROR(__xludf.DUMMYFUNCTION("""COMPUTED_VALUE"""),100.0) -> 100
A7: =IFERROR(__xludf.DUMMYFUNCTION("""COMPUTED_VALUE"""),"STO. ANTÔNIO DE ARACATIAÇU") -> STO. ANTÔNIO DE ARACATIAÇU | B7: =IFERROR(__xludf.DUMMYFUNCTION("""COMPUTED_VALUE"""),"Sobral") -> Sobral | C7: =IFERROR(__xludf.DUMMYFUNCTION("""COMPUTED_VALUE"""),92.67) -> 92.67 | D7: =IFERROR(__xludf.DUMMYFUNCTION("""COMPUTED_VALUE"""),92.65) -> 92.65 | E7: =IFERROR(__xludf.DUMMYFUNCTION("""COMPUTED_VALUE"""),-102653.0) -> -102653 | F7: =IFERROR(__xludf.DUMMYFUNCTION("""COMPUTED_VALUE"""),-0.02) -> -0.02 | G7: =IFERROR(__xludf.DUMMYFUNCTION("""COMPUTED_VALUE"""),-0.003580502267178235) -> -0.0035805023 | H7: =IFERROR(__xludf.DUMMYFUNCTION("""COMPUTED_VALUE"""),"#REF!") -> #REF! | I7: =IFERROR(__xludf.DUMMYFUNCTION("""COMPUTED_VALUE"""),26.88) -> 26.88 | J7: =IFERROR(__xludf.DUMMYFUNCTION("""COMPUTED_VALUE"""),93.74) -> 93.74
A8: =IFERROR(__xludf.DUMMYFUNCTION("""COMPUTED_VALUE"""),"PATOS") -> PATOS | B8: =IFERROR(__xludf.DUMMYFUNCTION("""COMPUTED_VALUE"""),"Sobral") -> Sobral | C8: =IFERROR(__xludf.DUMMYFUNCTION("""COMPUTED_VALUE"""),105.66) -> 105.66 | D8: =IFERROR(__xludf.DUMMYFUNCTION("""COMPUTED_VALUE"""),105.64) -> 105.64 | E8: =IFERROR(__xludf.DUMMYFUNCTION("""COMPUTED_VALUE"""),-38008.0) -> -38008 | F8: =IFERROR(__xludf.DUMMYFUNCTION("""COMPUTED_VALUE"""),-0.02) -> -0.02 | G8: =IFERROR(__xludf.DUMMYFUNCTION("""COMPUTED_VALUE"""),-0.0050341721854304635) -> -0.0050341722 | H8: =IFERROR(__xludf.DUMMYFUNCTION("""COMPUTED_VALUE"""),"#REF!") -> #REF! | I8: =IFERROR(__xludf.DUMMYFUNCTION("""COMPUTED_VALUE"""),6.87) -> 6.87 | J8: =IFERROR(__xludf.DUMMYFUNCTION("""COMPUTED_VALUE"""),90.94) -> 90.94

Sheet prog
A1: =IFERROR(__xludf.DUMMYFUNCTION("IMPORTRANGE(""https://docs.google.com/spreadsheets/d/1zaCmAHA_Hgob1ygsnCGPfEIosw5PR-DYRK7b89cprdc/edit?gid=1378782964#gid=1378782964"",""'Programação ITAPIPOCA'!A:E"")")," ")
B5: =IFERROR(__xludf.DUMMYFUNCTION("""COMPUTED_VALUE"""),"Gerência") -> Gerência | C5: =IFERROR(__xludf.DUMMYFUNCTION("""COMPUTED_VALUE"""),"Núcleo") -> Núcleo | D5: =IFERROR(__xludf.DUMMYFUNCTION("""COMPUTED_VALUE"""),"Eixo") -> Eixo | E5: =IFERROR(__xludf.DUMMYFUNCTION("""COMPUTED_VALUE"""),"Atividade") -> Atividade
E6: =IFERROR(__xludf.DUMMYFUNCTION("""COMPUTED_VALUE""")," ")
A7: =IFERROR(__xludf.DUMMYFUNCTION("""COMPUTED_VALUE"""),46027.0) -> 46027 | E7: =IFERROR(__xludf.DUMMYFUNCTION("""COMPUTED_VALUE"""),"Providenciar stories dos aniversariantes do mês de janeiro do CBH Litoral") -> Providenciar stories dos aniversariantes do mês de janeiro do CBH Litoral
A8: =IFERROR(__xludf.DUMMYFUNCTION("""COMPUTED_VALUE"""),46027.0) -> 46027 | E8: =IFERROR(__xludf.DUMMYFUNCTION("""COMPUTED_VALUE"""),"Organização de documentos para a mobilização de Diretoria") -> Organização de documentos para a mobilização de Diretoria
A9: =IFERROR(__xludf.DUMMYFUNCTION("""COMPUTED_VALUE"""),46027.0) -> 46027 | E9: =IFERROR(__xludf.DUMMYFUNCTION("""COMPUTED_VALUE"""),"Mobilização para a 1ª Reunião com a Diretoria do CBH Litoral") -> Mobilização para a 1ª Reunião com a Diretoria do CBH Litoral
A10: =IFERROR(__xludf.DUMMYFUNCTION("""COMPUTED_VALUE"""),46027.0) -> 46027 | E10: =IFERROR(__xludf.DUMMYFUNCTION("""COMPUTED_VALUE"""),"Faturamento (Coleta das leituras dos hidrômetros)") -> Faturamento (Coleta das leituras dos hidrômetros)
A11: =IFERROR(__xludf.DUMMYFUNCTION("""COMPUTED_VALUE"""),46027.0) -> 46027 | E11: =IFERROR(__xludf.DUMMYFUNCTION("""COMPUTED_VALUE"""),"Instrumentação dos açudes Missi e Poço Verde (Medidores de Vazão de Percolação)") -> Instrumentação dos açudes Missi e Poço Verde (Medidores de Vazão de Percolação)
A12: =IFERROR(__xludf.DUMMYFUNCTION("""COMPUTED_VALUE"""),46028.0) -> 46028 | E12: =IFERROR(__xludf.DUMMYFUNCTION("""COMPUTED_VALUE"""),"Publicar story do aniversário da Sra. Maria Ozani de Araújo Barros ") -> Publicar story do aniversário da Sra. Maria Ozani de Araújo Barros
A13: =IFERROR(__xludf.DUMMYFUNCTION("""COMPUTED_VALUE"""),46028.0) -> 46028 | E13: =IFERROR(__xludf.DUMMYFUNCTION("""COMPUTED_VALUE"""),"Produção de peça sobre a 1ª Reunião com a Diretoria do CBH Litoral") -> Produção de peça sobre a 1ª Reunião com a Diretoria do CBH Litoral
A14: =IFERROR(__xludf.DUMMYFUNCTION("""COMPUTED_VALUE"""),46028.0) -> 46028 | E14: =IFERROR(__xludf.DUMMYFUNCTION("""COMPUTED_VALUE"""),"Produção de apresentação das atividades realizadas em 2025") -> Produção de apresentação das atividades realizadas em 2025
A15: =IFERROR(__xludf.DUMMYFUNCTION("""COMPUTED_VALUE"""),46028.0) -> 46028 | E15: =IFERROR(__xludf.DUMMYFUNCTION("""COMPUTED_VALUE"""),"Planejamento comunicação do CBH Litoral") -> Planejamento comunicação do CBH Litoral
A16: =IFERROR(__xludf.DUMMYFUNCTION("""COMPUTED_VALUE"""),46028.0) -> 46028 | E16: =IFERROR(__xludf.DUMMYFUNCTION("""COMPUTED_VALUE"""),"Contato com a comunicação da SRH para gravação de vídeo sobre o Dia Internacional da Educação") -> Contato com a comunicação da SRH para gravação de vídeo sobre o Dia Internacional da Educação
A17: =IFERROR(__xludf.DUMMYFUNCTION("""COMPUTED_VALUE"""),46028.0) -> 46028 | E17: =IFERROR(__xludf.DUMMYFUNCTION("""COMPUTED_VALUE"""),"Faturamento (Coleta das leituras dos hidrômetros)") -> Faturamento (Coleta das leituras dos hidrômetros)
A18: =IFERROR(__xludf.DUMMYFUNCTION("""COMPUTED_VALUE"""),46028.0) -> 46028 | E18: =IFERROR(__xludf.DUMMYFUNCTION("""COMPUTED_VALUE"""),"Acompanhamento de Trecho Perenizado (Mundaú)") -> Acompanhamento de Trecho Perenizado (Mundaú)
A19: =IFERROR(__xludf.DUMMYFUNCTION("""COMPUTED_VALUE"""),46029.0) -> 46029 | E19: =IFERROR(__xludf.DUMMYFUNCTION("""COMPUTED_VALUE"""),"Produção de apresentação das atividades realizadas em 2025") -> Produção de apresentação das atividades realizadas em 2025
A20: =IFERROR(__xludf.DUMMYFUNCTION("""COMPUTED_VALUE"""),46029.0) -> 46029 | E20: =IFERROR(__xludf.DUMMYFUNCTION("""COMPUTED_VALUE"""),"Providenciar série de publicações sobre a campanha Janeiro Branco") -> Providenciar série de publicações sobre a campanha Janeiro Branco
A21: =IFERROR(__xludf.DUMMYFUNCTION("""COMPUTED_VALUE"""),46029.0) -> 46029 | E21: =IFERROR(__xludf.DUMMYFUNCTION("""COMPUTED_VALUE"""),"Faturamento (Coleta das leituras dos hidrômetros)") -> Faturamento (Coleta das leituras dos hidrômetros)
A22: =IFERROR(__xludf.DUMMYFUNCTION("""COMPUTED_VALUE"""),46029.0) -> 46029 | E22: =IFERROR(__xludf.DUMMYFUNCTION("""COMPUTED_VALUE"""),"Inspeção de Segurança Regular, Acompanhamento de Trecho Perenizado e Medição de Vazão (São Pedro da Timbaúba)") -> Inspeção de Segurança Regular, Acompanhamento de Trecho Perenizado e Medição de Vazão (São Pedro da Timbaúba)
A23: =IFERROR(__xludf.DUMMYFUNCTION("""COMPUTED_VALUE"""),46030.0) -> 46030 | E23: =IFERROR(__xludf.DUMMYFUNCTION("""COMPUTED_VALUE"""),"Oficina: Uso de IA no apoio à elaboração e padronização de atas e relatórios na COGERH") -> Oficina: Uso de IA no apoio à elaboração e padronização de atas e relatórios na COGERH
A24: =IFERROR(__xludf.DUMMYFUNCTION("""COMPUTED_VALUE"""),46030.0) -> 46030 | E24: =IFERROR(__xludf.DUMMYFUNCTION("""COMPUTED_VALUE"""),"Providenciar peça sobre emancipação do Estado do Ceará") -> Providenciar peça sobre emancipação do Estado do Ceará
A25: =IFERROR(__xludf.DUMMYFUNCTION("""COMPUTED_VALUE"""),46030.0) -> 46030 | E25: =IFERROR(__xludf.DUMMYFUNCTION("""COMPUTED_VALUE"""),"Faturamento (Coleta das leituras dos hidrômetros) e Vistoria no Trairi referente à contrução de um tanque") -> Faturamento (Coleta das leituras dos hidrômetros) e Vistoria no Trairi referente à contrução de um tanque
A26: =IFERROR(__xludf.DUMMYFUNCTION("""COMPUTED_VALUE"""),46030.0) -> 46030 | E26: =IFERROR(__xludf.DUMMYFUNCTION("""COMPUTED_VALUE"""),"Produção de Relatório de Acompanhamento de Trecho Perenizado (Mundaú e São Pedro da Timbaúba)") -> Produção de Relatório de Acompanhamento de Trecho Perenizado (Mundaú e São Pedro da Timbaúba)
A27: =IFERROR(__xludf.DUMMYFUNCTION("""COMPUTED_VALUE"""),46030.0) -> 46030 | E27: =IFERROR(__xludf.DUMMYFUNCTION("""COMPUTED_VALUE"""),"Inserir dados do Checklist no SIGERH (São Pedro da Timbaúba)") -> Inserir dados do Checklist no SIGERH (São Pedro da Timbaúba)
A28: =IFERROR(__xludf.DUMMYFUNCTION("""COMPUTED_VALUE"""),46031.0) -> 46031 | E28: =IFERROR(__xludf.DUMMYFUNCTION("""COMPUTED_VALUE"""),"Retorno da oficina: Uso de IA no apoio à elaboração e padronização de atas e relatórios na COGERH") -> Retorno da oficina: Uso de IA no apoio à elaboração e padronização de atas e relatórios na COGERH
A29: =IFERROR(__xludf.DUMMYFUNCTION("""COMPUTED_VALUE"""),46031.0) -> 46031 | E29: =IFERROR(__xludf.DUMMYFUNCTION("""COMPUTED_VALUE"""),"Produção de matéria sobre a 1ª Reunião com a Diretoria") -> Produção de matéria sobre a 1ª Reunião com a Diretoria
A30: =IFERROR(__xludf.DUMMYFUNCTION("""COMPUTED_VALUE"""),46031.0) -> 46031 | E30: =IFERROR(__xludf.DUMMYFUNCTION("""COMPUTED_VALUE"""),"Atualizar planilha da Gerência Regional com atividades programadas da semana") -> Atualizar planilha da Gerência Regional com atividades programadas da semana
A31: =IFERROR(__xludf.DUMMYFUNCTION("""COMPUTED_VALUE"""),46031.0) -> 46031 | E31: =IFERROR(__xludf.DUMMYFUNCTION("""COMPUTED_VALUE"""),"Atualizar planilha da Gestão Participativa com atividades programadas da semana") -> Atualizar planilha da Gestão Participativa com atividades programadas da semana
A32: =IFERROR(__xludf.DUMMYFUNCTION("""COMPUTED_VALUE"""),46031.0) -> 46031 | E32: =IFERROR(__xludf.DUMMYFUNCTION("""COMPUTED_VALUE"""),"Faturamento (Atualizar dados do faturamento no sistema)") -> Faturamento (Atualizar dados do faturamento no sistema)
A33: =IFERROR(__xludf.DUMMYFUNCTION("""COMPUTED_VALUE"""),46031.0) -> 46031 | E33: =IFERROR(__xludf.DUMMYFUNCTION("""COMPUTED_VALUE"""),"Vistoria de Usuários (DASS)") -> Vistoria de Usuários (DASS)
A34: =IFERROR(__xludf.DUMMYFUNCTION("""COMPUTED_VALUE"""),46031.0) -> 46031 | E34: =IFERROR(__xludf.DUMMYFUNCTION("""COMPUTED_VALUE"""),"Produção do relatório de vistoria na DASS") -> Produção do relatório de vistoria na DASS
A35: =IFERROR(__xludf.DUMMYFUNCTION("""COMPUTED_VALUE"""),46031.0) -> 46031 | E35: =IFERROR(__xludf.DUMMYFUNCTION("""COMPUTED_VALUE"""),"Atualização dos dados de Captação e Perenização no SIGERH") -> Atualização dos dados de Captação e Perenização no SIGERH
A36: =IFERROR(__xludf.DUMMYFUNCTION("""COMPUTED_VALUE"""),46031.0) -> 46031 | E36: =IFERROR(__xludf.DUMMYFUNCTION("""COMPUTED_VALUE"""),"Instrumentação dos açudes Missi e Poço Verde (Medidores de Vazão de Percolação)") -> Instrumentação dos açudes Missi e Poço Verde (Medidores de Vazão de Percolação)
A37: =IFERROR(__xludf.DUMMYFUNCTION("""COMPUTED_VALUE"""),46032.0) -> 46032
A38: =IFERROR(__xludf.DUMMYFUNCTION("""COMPUTED_VALUE"""),46033.0) -> 46033
A39: =IFERROR(__xludf.DUMMYFUNCTION("""COMPUTED_VALUE"""),46034.0) -> 46034 | E39: =IFERROR(__xludf.DUMMYFUNCTION("""COMPUTED_VALUE"""),"Diagnóstico CG do açude Patos") -> Diagnóstico CG do açude Patos
A40: =IFERROR(__xludf.DUMMYFUNCTION("""COMPUTED_VALUE"""),46034.0) -> 46034 | E40: =IFERROR(__xludf.DUMMYFUNCTION("""COMPUTED_VALUE"""),"Atualizar contatos das Câmaras e Prefeituras Municipais dos 13 municípios da Bacia Hidrográfica") -> Atualizar contatos das Câmaras e Prefeituras Municipais dos 13 municípios da Bacia Hidrográfica
A41: =IFERROR(__xludf.DUMMYFUNCTION("""COMPUTED_VALUE"""),46034.0) -> 46034 | E41: =IFERROR(__xludf.DUMMYFUNCTION("""COMPUTED_VALUE"""),"Organizar rota de mobilizações para a 74ª Reunião Ordinária") -> Organizar rota de mobilizações para a 74ª Reunião Ordinária
A42: =IFERROR(__xludf.DUMMYFUNCTION("""COMPUTED_VALUE"""),46034.0) -> 46034 | E42: =IFERROR(__xludf.DUMMYFUNCTION("""COMPUTED_VALUE"""),"Comunicar os membros que gravarão os vídeos dos aniversários municipais de Itarema e Amontada, respectivamente") -> Comunicar os membros que gravarão os vídeos dos aniversários municipais de Itarema e Amontada, respectivamente
A43: =IFERROR(__xludf.DUMMYFUNCTION("""COMPUTED_VALUE"""),46034.0) -> 46034 | E43: =IFERROR(__xludf.DUMMYFUNCTION("""COMPUTED_VALUE"""),"Produção de post com legenda sobre 74ª Reunião Ordinária do CBH Litoral") -> Produção de post com legenda sobre 74ª Reunião Ordinária do CBH Litoral
A44: =IFERROR(__xludf.DUMMYFUNCTION("""COMPUTED_VALUE"""),46034.0) -> 46034 | E44: =IFERROR(__xludf.DUMMYFUNCTION("""COMPUTED_VALUE"""),"Inspeção de Segurança Regular e Medição de Vazão (Patos)") -> Inspeção de Segurança Regular e Medição de Vazão (Patos)
A45: =IFERROR(__xludf.DUMMYFUNCTION("""COMPUTED_VALUE"""),46035.0) -> 46035 | E45: =IFERROR(__xludf.DUMMYFUNCTION("""COMPUTED_VALUE"""),"Diagnóstico CG do açude Patos") -> Diagnóstico CG do açude Patos
A46: =IFERROR(__xludf.DUMMYFUNCTION("""COMPUTED_VALUE"""),46035.0) -> 46035 | E46: =IFERROR(__xludf.DUMMYFUNCTION("""COMPUTED_VALUE"""),"Produção de apresentação das atividades realizadas em 2025") -> Produção de apresentação das atividades realizadas em 2025
A47: =IFERROR(__xludf.DUMMYFUNCTION("""COMPUTED_VALUE"""),46035.0) -> 46035 | E47: =IFERROR(__xludf.DUMMYFUNCTION("""COMPUTED_VALUE"""),"Reforçar contato com a comunicação da SRH para gravação de vídeo sobre o Dia Internacional da Educação") -> Reforçar contato com a comunicação da SRH para gravação de vídeo sobre o Dia Internacional da Educação
A48: =IFERROR(__xludf.DUMMYFUNCTION("""COMPUTED_VALUE"""),46035.0) -> 46035 | E48: =IFERROR(__xludf.DUMMYFUNCTION("""COMPUTED_VALUE"""),"Coleta para Análise Qualitativa da Água (Gameleira e Poço Verde)") -> Coleta para Análise Qualitativa da Água (Gameleira e Poço Verde)
A49: =IFERROR(__xludf.DUMMYFUNCTION("""COMPUTED_VALUE"""),46036.0) -> 46036 | E49: =IFERROR(__xludf.DUMMYFUNCTION("""COMPUTED_VALUE"""),"Diagnóstico CG do açude Patos") -> Diagnóstico CG do açude Patos
A50: =IFERROR(__xludf.DUMMYFUNCTION("""COMPUTED_VALUE"""),46036.0) -> 46036 | E50: =IFERROR(__xludf.DUMMYFUNCTION("""COMPUTED_VALUE"""),"Apoio na limpeza do açude São Pedro da Timbaúba") -> Apoio na limpeza do açude São Pedro da Timbaúba
A51: =IFERROR(__xludf.DUMMYFUNCTION("""COMPUTED_VALUE"""),46036.0) -> 46036 | E51: =IFERROR(__xludf.DUMMYFUNCTION("""COMPUTED_VALUE"""),"Publicação Janeiro Branco") -> Publicação Janeiro Branco
A52: =IFERROR(__xludf.DUMMYFUNCTION("""COMPUTED_VALUE"""),46036.0) -> 46036 | E52: =IFERROR(__xludf.DUMMYFUNCTION("""COMPUTED_VALUE"""),"Prazo limite/final para providenciar e enviar as atividades programadas de fevereiro para GEPAR") -> Prazo limite/final para providenciar e enviar as atividades programadas de fevereiro para GEPAR
A53: =IFERROR(__xludf.DUMMYFUNCTION("""COMPUTED_VALUE"""),46036.0) -> 46036 | E53: =IFERROR(__xludf.DUMMYFUNCTION("""COMPUTED_VALUE"""),"Coleta para Análise Qualitativa da Água (Mundaú e Quandu)") -> Coleta para Análise Qualitativa da Água (Mundaú e Quandu)
A54: =IFERROR(__xludf.DUMMYFUNCTION("""COMPUTED_VALUE"""),46037.0) -> 46037 | E54: =IFERROR(__xludf.DUMMYFUNCTION("""COMPUTED_VALUE"""),"Apoio logístico para Fabiana Castro, vice-presidente do CBH Litoral") -> Apoio logístico para Fabiana Castro, vice-presidente do CBH Litoral
A55: =IFERROR(__xludf.DUMMYFUNCTION("""COMPUTED_VALUE"""),46037.0) -> 46037 | E55: =IFERROR(__xludf.DUMMYFUNCTION("""COMPUTED_VALUE"""),"1ª Reunião com a Diretoria do CBH Litoral") -> 1ª Reunião com a Diretoria do CBH Litoral
A56: =IFERROR(__xludf.DUMMYFUNCTION("""COMPUTED_VALUE"""),46037.0) -> 46037 | E56: =IFERROR(__xludf.DUMMYFUNCTION("""COMPUTED_VALUE"""),"Produção de ata da 1ª Reunião com a Diretoria do CBH Litoral") -> Produção de ata da 1ª Reunião com a Diretoria do CBH Litoral
A57: =IFERROR(__xludf.DUMMYFUNCTION("""COMPUTED_VALUE"""),46037.0) -> 46037 | E57: =IFERROR(__xludf.DUMMYFUNCTION("""COMPUTED_VALUE"""),"Publicação de matéria e post sobre a 1ª Reunião com a Diretoria do CBH Litoral") -> Publicação de matéria e post sobre a 1ª Reunião com a Diretoria do CBH Litoral
A58: =IFERROR(__xludf.DUMMYFUNCTION("""COMPUTED_VALUE"""),46037.0) -> 46037 | E58: =IFERROR(__xludf.DUMMYFUNCTION("""COMPUTED_VALUE"""),"Produção de post com legenda sobre o Dia Internacional da Educação") -> Produção de post com legenda sobre o Dia Internacional da Educação
A59: =IFERROR(__xludf.DUMMYFUNCTION("""COMPUTED_VALUE"""),46037.0) -> 46037 | E59: =IFERROR(__xludf.DUMMYFUNCTION("""COMPUTED_VALUE"""),"Gravação sobre o Dia do Agente de Defesa Ambiental") -> Gravação sobre o Dia do Agente de Defesa Ambiental
A60: =IFERROR(__xludf.DUMMYFUNCTION("""COMPUTED_VALUE"""),46037.0) -> 46037 | E60: =IFERROR(__xludf.DUMMYFUNCTION("""COMPUTED_VALUE"""),"Produção de apresentação das atividades realizadas em 2024") -> Produção de apresentação das atividades realizadas em 2024
A61: =IFERROR(__xludf.DUMMYFUNCTION("""COMPUTED_VALUE"""),46037.0) -> 46037 | E61: =IFERROR(__xludf.DUMMYFUNCTION("""COMPUTED_VALUE"""),"Inserir dados das Coletas no SIGERH") -> Inserir dados das Coletas no SIGERH
A62: =IFERROR(__xludf.DUMMYFUNCTION("""COMPUTED_VALUE"""),46037.0) -> 46037 | E62: =IFERROR(__xludf.DUMMYFUNCTION("""COMPUTED_VALUE"""),"Instrumentação do açude Missi (Piezômetros)") -> Instrumentação do açude Missi (Piezômetros)
A63: =IFERROR(__xludf.DUMMYFUNCTION("""COMPUTED_VALUE"""),46037.0) -> 46037 | E63: =IFERROR(__xludf.DUMMYFUNCTION("""COMPUTED_VALUE"""),"Condensar informações do Diagnóstico do Açude Patos") -> Condensar informações do Diagnóstico do Açude Patos
A64: =IFERROR(__xludf.DUMMYFUNCTION("""COMPUTED_VALUE"""),46038.0) -> 46038 | E64: =IFERROR(__xludf.DUMMYFUNCTION("""COMPUTED_VALUE"""),"Providenciar CI para a 74ª Reunião Ordinária do CBH Litoral") -> Providenciar CI para a 74ª Reunião Ordinária do CBH Litoral
A65: =IFERROR(__xludf.DUMMYFUNCTION("""COMPUTED_VALUE"""),46038.0) -> 46038 | E65: =IFERROR(__xludf.DUMMYFUNCTION("""COMPUTED_VALUE"""),"Oficializar espaço para a 74ª Reunião Ordinária do CBH Litoral") -> Oficializar espaço para a 74ª Reunião Ordinária do CBH Litoral
A66: =IFERROR(__xludf.DUMMYFUNCTION("""COMPUTED_VALUE"""),46038.0) -> 46038 | E66: =IFERROR(__xludf.DUMMYFUNCTION("""COMPUTED_VALUE"""),"Organizar convocatórias para as mobilizações da 74ª Reunião Ordinária do CBH Litoral") -> Organizar convocatórias para as mobilizações da 74ª Reunião Ordinária do CBH Litoral
A67: =IFERROR(__xludf.DUMMYFUNCTION("""COMPUTED_VALUE"""),46038.0) -> 46038 | E67: =IFERROR(__xludf.DUMMYFUNCTION("""COMPUTED_VALUE"""),"Atualizar planilha da Gerência Regional com atividades programadas da semana") -> Atualizar planilha da Gerência Regional com atividades programadas da semana
A68: =IFERROR(__xludf.DUMMYFUNCTION("""COMPUTED_VALUE"""),46038.0) -> 46038 | E68: =IFERROR(__xludf.DUMMYFUNCTION("""COMPUTED_VALUE"""),"Atualizar planilha da Gestão Participativa com atividades programadas da semana") -> Atualizar planilha da Gestão Participativa com atividades programadas da semana
A69: =IFERROR(__xludf.DUMMYFUNCTION("""COMPUTED_VALUE"""),46038.0) -> 46038 | E69: =IFERROR(__xludf.DUMMYFUNCTION("""COMPUTED_VALUE"""),"Inspeção de Segurança Regular (Mundaú)") -> Inspeção de Segurança Regular (Mundaú)
A70: =IFERROR(__xludf.DUMMYFUNCTION("""COMPUTED_VALUE"""),46038.0) -> 46038 | E70: =IFERROR(__xludf.DUMMYFUNCTION("""COMPUTED_VALUE"""),"Vistoria de Usuários (Obtenção de novos usuários)") -> Vistoria de Usuários (Obtenção de novos usuários)
A71: =IFERROR(__xludf.DUMMYFUNCTION("""COMPUTED_VALUE"""),46038.0) -> 46038 | E71: =IFERROR(__xludf.DUMMYFUNCTION("""COMPUTED_VALUE"""),"Atualização dos dados de Captação e Perenização no SIGERH") -> Atualização dos dados de Captação e Perenização no SIGERH
A72: =IFERROR(__xludf.DUMMYFUNCTION("""COMPUTED_VALUE"""),46038.0) -> 46038 | E72: =IFERROR(__xludf.DUMMYFUNCTION("""COMPUTED_VALUE"""),"Instrumentação dos açudes Missi e Poço Verde (Medidores de Vazão de Percolação)") -> Instrumentação dos açudes Missi e Poço Verde (Medidores de Vazão de Percolação)
A73: =IFERROR(__xludf.DUMMYFUNCTION("""COMPUTED_VALUE"""),46039.0) -> 46039 | E73: =IFERROR(__xludf.DUMMYFUNCTION("""COMPUTED_VALUE"""),"Publicação de story sobre a emancipação política do Estado do Ceará") -> Publicação de story sobre a emancipação política do Estado do Ceará
A74: =IFERROR(__xludf.DUMMYFUNCTION("""COMPUTED_VALUE"""),46040.0) -> 46040
A75: =IFERROR(__xludf.DUMMYFUNCTION("""COMPUTED_VALUE"""),46041.0) -> 46041 | E75: =IFERROR(__xludf.DUMMYFUNCTION("""COMPUTED_VALUE"""),"Inserir dados do Checklist no SIGERH (Mundaú)") -> Inserir dados do Checklist no SIGERH (Mundaú)
A76: =IFERROR(__xludf.DUMMYFUNCTION("""COMPUTED_VALUE"""),46041.0) -> 46041 | E76: =IFERROR(__xludf.DUMMYFUNCTION("""COMPUTED_VALUE"""),"Enviar frascos das Coletas aos Correios") -> Enviar frascos das Coletas aos Correios
A77: =IFERROR(__xludf.DUMMYFUNCTION("""COMPUTED_VALUE"""),46041.0) -> 46041 | E77: =IFERROR(__xludf.DUMMYFUNCTION("""COMPUTED_VALUE"""),"Acompanhamento das equipes do estudo sobre uso de poços") -> Acompanhamento das equipes do estudo sobre uso de poços
A78: =IFERROR(__xludf.DUMMYFUNCTION("""COMPUTED_VALUE"""),46042.0) -> 46042 | E78: =IFERROR(__xludf.DUMMYFUNCTION("""COMPUTED_VALUE"""),"FERIADO MUNICIPAL DE SÃO SEBASTIÃO") -> FERIADO MUNICIPAL DE SÃO SEBASTIÃO
A79: =IFERROR(__xludf.DUMMYFUNCTION("""COMPUTED_VALUE"""),46043.0) -> 46043 | E79: =IFERROR(__xludf.DUMMYFUNCTION("""COMPUTED_VALUE"""),"Publicação de post com legenda sobre 74ª Reunião Ordinária do CBH Litoral") -> Publicação de post com legenda sobre 74ª Reunião Ordinária do CBH Litoral
A80: =IFERROR(__xludf.DUMMYFUNCTION("""COMPUTED_VALUE"""),46043.0) -> 46043 | E80: =IFERROR(__xludf.DUMMYFUNCTION("""COMPUTED_VALUE"""),"Mobilização 74ª Reunião Ordinária do CBH Litoral ") -> Mobilização 74ª Reunião Ordinária do CBH Litoral
A81: =IFERROR(__xludf.DUMMYFUNCTION("""COMPUTED_VALUE"""),46043.0) -> 46043 | E81: =IFERROR(__xludf.DUMMYFUNCTION("""COMPUTED_VALUE"""),"Providenciar story sobre o Dia do Engenheiro Ambiental") -> Providenciar story sobre o Dia do Engenheiro Ambiental
A82: =IFERROR(__xludf.DUMMYFUNCTION("""COMPUTED_VALUE"""),46043.0) -> 46043 | E82: =IFERROR(__xludf.DUMMYFUNCTION("""COMPUTED_VALUE"""),"Acompanhamento de Trecho Perenizado (Quandú)") -> Acompanhamento de Trecho Perenizado (Quandú)
A83: =IFERROR(__xludf.DUMMYFUNCTION("""COMPUTED_VALUE"""),46043.0) -> 46043 | E83: =IFERROR(__xludf.DUMMYFUNCTION("""COMPUTED_VALUE"""),"Revisão das Inspeções de Segurança Regular") -> Revisão das Inspeções de Segurança Regular
A84: =IFERROR(__xludf.DUMMYFUNCTION("""COMPUTED_VALUE"""),46043.0) -> 46043 | E84: =IFERROR(__xludf.DUMMYFUNCTION("""COMPUTED_VALUE"""),"Acompanhamento das equipes do estudo sobre uso de poços") -> Acompanhamento das equipes do estudo sobre uso de poços
A85: =IFERROR(__xludf.DUMMYFUNCTION("""COMPUTED_VALUE"""),46044.0) -> 46044 | E85: =IFERROR(__xludf.DUMMYFUNCTION("""COMPUTED_VALUE"""),"Publicar story do aniversário da Sra. Cleonice Nascimento do Carmo (Conselho Indígena Tremembé de Itapipoca)") -> Publicar story do aniversário da Sra. Cleonice Nascimento do Carmo (Conselho Indígena Tremembé de Itapipoca)
A86: =IFERROR(__xludf.DUMMYFUNCTION("""COMPUTED_VALUE"""),46044.0) -> 46044 | E86: =IFERROR(__xludf.DUMMYFUNCTION("""COMPUTED_VALUE"""),"Mobilização 74ª Reunião Ordinária do CBH Litoral ") -> Mobilização 74ª Reunião Ordinária do CBH Litoral
A87: =IFERROR(__xludf.DUMMYFUNCTION("""COMPUTED_VALUE"""),46044.0) -> 46044 | E87: =IFERROR(__xludf.DUMMYFUNCTION("""COMPUTED_VALUE"""),"Produção de peça sobre a 2ª Reunião com a Diretoria do CBH Litoral ") -> Produção de peça sobre a 2ª Reunião com a Diretoria do CBH Litoral
A88: =IFERROR(__xludf.DUMMYFUNCTION("""COMPUTED_VALUE"""),46044.0) -> 46044 | E88: =IFERROR(__xludf.DUMMYFUNCTION("""COMPUTED_VALUE"""),"Vistoria (Cerca irregular no açude Poço Verde)") -> Vistoria (Cerca irregular no açude Poço Verde)
A89: =IFERROR(__xludf.DUMMYFUNCTION("""COMPUTED_VALUE"""),46044.0) -> 46044 | E89: =IFERROR(__xludf.DUMMYFUNCTION("""COMPUTED_VALUE"""),"Acompanhamento de Trecho Perenizado (Mundaú)") -> Acompanhamento de Trecho Perenizado (Mundaú)
A90: =IFERROR(__xludf.DUMMYFUNCTION("""COMPUTED_VALUE"""),46044.0) -> 46044 | E90: =IFERROR(__xludf.DUMMYFUNCTION("""COMPUTED_VALUE"""),"Acompanhamento das equipes do estudo sobre uso de poços") -> Acompanhamento das equipes do estudo sobre uso de poços
A91: =IFERROR(__xludf.DUMMYFUNCTION("""COMPUTED_VALUE"""),46044.0) -> 46044 | E91: =IFERROR(__xludf.DUMMYFUNCTION("""COMPUTED_VALUE"""),"Revisão das Inspeções de Segurança Regular") -> Revisão das Inspeções de Segurança Regular
A92: =IFERROR(__xludf.DUMMYFUNCTION("""COMPUTED_VALUE"""),46045.0) -> 46045 | E92: =IFERROR(__xludf.DUMMYFUNCTION("""COMPUTED_VALUE"""),"Mobilização 74ª Reunião Ordinária do CBH Litoral") -> Mobilização 74ª Reunião Ordinária do CBH Litoral
A93: =IFERROR(__xludf.DUMMYFUNCTION("""COMPUTED_VALUE"""),46045.0) -> 46045 | E93: =IFERROR(__xludf.DUMMYFUNCTION("""COMPUTED_VALUE"""),"Gravação aniversário de emancipação de Amontada") -> Gravação aniversário de emancipação de Amontada
A94: =IFERROR(__xludf.DUMMYFUNCTION("""COMPUTED_VALUE"""),46045.0) -> 46045 | E94: =IFERROR(__xludf.DUMMYFUNCTION("""COMPUTED_VALUE"""),"Atualizar planilha da Gerência Regional com atividades programadas da semana") -> Atualizar planilha da Gerência Regional com atividades programadas da semana
A95: =IFERROR(__xludf.DUMMYFUNCTION("""COMPUTED_VALUE"""),46045.0) -> 46045 | E95: =IFERROR(__xludf.DUMMYFUNCTION("""COMPUTED_VALUE"""),"Atualizar planilha da Gestão Participativa com atividades programadas da semana ") -> Atualizar planilha da Gestão Participativa com atividades programadas da semana
A96: =IFERROR(__xludf.DUMMYFUNCTION("""COMPUTED_VALUE"""),46045.0) -> 46045 | E96: =IFERROR(__xludf.DUMMYFUNCTION("""COMPUTED_VALUE"""),"Inspeçao de segurança Regular e Medição de Vazão (Sto Ant aracatiaçu)") -> Inspeçao de segurança Regular e Medição de Vazão (Sto Ant aracatiaçu)
A97: =IFERROR(__xludf.DUMMYFUNCTION("""COMPUTED_VALUE"""),46045.0) -> 46045 | E97: =IFERROR(__xludf.DUMMYFUNCTION("""COMPUTED_VALUE"""),"Atualização dos dados de Captação e Perenização no SIGERH") -> Atualização dos dados de Captação e Perenização no SIGERH
A98: =IFERROR(__xludf.DUMMYFUNCTION("""COMPUTED_VALUE"""),46045.0) -> 46045 | E98: =IFERROR(__xludf.DUMMYFUNCTION("""COMPUTED_VALUE"""),"Relatorio de acompanhamento de trecho do Quandu e Mundaú") -> Relatorio de acompanhamento de trecho do Quandu e Mundaú
A99: =IFERROR(__xludf.DUMMYFUNCTION("""COMPUTED_VALUE"""),46045.0) -> 46045 | E99: =IFERROR(__xludf.DUMMYFUNCTION("""COMPUTED_VALUE"""),"Instrumentação dos açudes Missi e Poço Verde (Medidores de Vazão de Percolação)") -> Instrumentação dos açudes Missi e Poço Verde (Medidores de Vazão de Percolação)
A100: =IFERROR(__xludf.DUMMYFUNCTION("""COMPUTED_VALUE"""),46045.0) -> 46045 | E100: =IFERROR(__xludf.DUMMYFUNCTION("""COMPUTED_VALUE"""),"Acompanhamento das equipes do estudo sobre uso de poços") -> Acompanhamento das equipes do estudo sobre uso de poços
A101: =IFERROR(__xludf.DUMMYFUNCTION("""COMPUTED_VALUE"""),46046.0) -> 46046 | E101: =IFERROR(__xludf.DUMMYFUNCTION("""COMPUTED_VALUE"""),"Publicar story sobre o Dia de Agente de Defesa Ambiental") -> Publicar story sobre o Dia de Agente de Defesa Ambiental
A102: =IFERROR(__xludf.DUMMYFUNCTION("""COMPUTED_VALUE"""),46047.0) -> 46047
A103: =IFERROR(__xludf.DUMMYFUNCTION("""COMPUTED_VALUE"""),46048.0) -> 46048 | E103: =IFERROR(__xludf.DUMMYFUNCTION("""COMPUTED_VALUE"""),"Mobilização 74ª Reunião Ordinária do CBH Litoral E Gravação aniversário de emancipação de Itarema") -> Mobilização 74ª Reunião Ordinária do CBH Litoral E Gravação aniversário de emancipação de Itarema
...

Sheet oper
A1: FISCALIZAÇÃO
A2: =IFERROR(__xludf.DUMMYFUNCTION("IMPORTRANGE(""https://docs.google.com/spreadsheets/d/1iBrpLlm14k9_yhp3qCf1sI5I4CW0_hVvSluhMLtsnf0/edit?gid=874251860#gid=874251860"",""Indicador Setorial!b4:O4"")"),105.0) -> 105 | B2: =IFERROR(__xludf.DUMMYFUNCTION("""COMPUTED_VALUE"""),38.0) -> 38 | C2: =IFERROR(__xludf.DUMMYFUNCTION("""COMPUTED_VALUE"""),7.0) -> 7 | D2: =IFERROR(__xludf.DUMMYFUNCTION("""COMPUTED_VALUE"""),4.0) -> 4 | E2: =IFERROR(__xludf.DUMMYFUNCTION("""COMPUTED_VALUE"""),8.0) -> 8 | F2: =IFERROR(__xludf.DUMMYFUNCTION("""COMPUTED_VALUE"""),9.0) -> 9 | G2: =IFERROR(__xludf.DUMMYFUNCTION("""COMPUTED_VALUE"""),10.0) -> 10 | H2: =IFERROR(__xludf.DUMMYFUNCTION("""COMPUTED_VALUE"""),0.0) -> 0 | I2: =IFERROR(__xludf.DUMMYFUNCTION("""COMPUTED_VALUE"""),0.0) -> 0 | J2: =IFERROR(__xludf.DUMMYFUNCTION("""COMPUTED_VALUE"""),0.0) -> 0 | K2: =IFERROR(__xludf.DUMMYFUNCTION("""COMPUTED_VALUE"""),0.0) -> 0 | L2: =IFERROR(__xludf.DUMMYFUNCTION("""COMPUTED_VALUE"""),0.0) -> 0 | M2: =IFERROR(__xludf.DUMMYFUNCTION("""COMPUTED_VALUE"""),0.0) -> 0 | N2: =IFERROR(__xludf.DUMMYFUNCTION("""COMPUTED_VALUE"""),0.0) -> 0 | O2: SEM RV
C3: =IFERROR(__xludf.DUMMYFUNCTION("IMPORTRANGE(""https://docs.google.com/spreadsheets/d/1iBrpLlm14k9_yhp3qCf1sI5I4CW0_hVvSluhMLtsnf0/edit?gid=874251860#gid=874251860"",""Indicador Setorial!d31:31"")"),5.0) -> 5 | D3: =IFERROR(__xludf.DUMMYFUNCTION("""COMPUTED_VALUE"""),3.0) -> 3 | E3: =IFERROR(__xludf.DUMMYFUNCTION("""COMPUTED_VALUE"""),5.0) -> 5 | F3: =IFERROR(__xludf.DUMMYFUNCTION("""COMPUTED_VALUE"""),0.0) -> 0 | G3: =IFERROR(__xludf.DUMMYFUNCTION("""COMPUTED_VALUE"""),0.0) -> 0 | H3: =IFERROR(__xludf.DUMMYFUNCTION("""COMPUTED_VALUE"""),0.0) -> 0 | I3: =IFERROR(__xludf.DUMMYFUNCTION("""COMPUTED_VALUE"""),0.0) -> 0 | J3: =IFERROR(__xludf.DUMMYFUNCTION("""COMPUTED_VALUE"""),0.0) -> 0 | K3: =IFERROR(__xludf.DUMMYFUNCTION("""COMPUTED_VALUE"""),0.0) -> 0 | L3: =IFERROR(__xludf.DUMMYFUNCTION("""COMPUTED_VALUE"""),0.0) -> 0 | M3: =IFERROR(__xludf.DUMMYFUNCTION("""COMPUTED_VALUE"""),0.0) -> 0 | N3: =IFERROR(__xludf.DUMMYFUNCTION("""COMPUTED_VALUE"""),0.0) -> 0 | O3: =IFERROR(__xludf.DUMMYFUNCTION("""COMPUTED_VALUE"""),13.0) -> 13
A5: MANUTENÇÃO E INSTALAÇÃO:
C6: =IFERROR(__xludf.DUMMYFUNCTION("IMPORTRANGE(""https://docs.google.com/spreadsheets/d/1ZMQ1ZJd0nWMp1bKte4MwmpuiYfPuptkAdyS2OLhz2tY/edit?gid=867584558#gid=867584558"",""Itapipoca!B1:G1"")"),"MEDIÇÕES DE VAZÃO (MEDV)") -> MEDIÇÕES DE VAZÃO (MEDV) | D6: =IFERROR(__xludf.DUMMYFUNCTION("""COMPUTED_VALUE"""),"MEDIÇÕES COMPARATIVAS (MEDC)") -> MEDIÇÕES COMPARATIVAS (MEDC) | E6: =IFERROR(__xludf.DUMMYFUNCTION("""COMPUTED_VALUE"""),"MANUTENÇÕES DE HORIMETROS (MANH)") -> MANUTENÇÕES DE HORIMETROS (MANH) | F6: =IFERROR(__xludf.DUMMYFUNCTION("""COMPUTED_VALUE"""),"MANUTENÇÕES DE MEDIDORES (MANM)") -> MANUTENÇÕES DE MEDIDORES (MANM) | G6: =IFERROR(__xludf.DUMMYFUNCTION("""COMPUTED_VALUE"""),"INSTALAÇÕES DE HORIMETROS (INSH)") -> INSTALAÇÕES DE HORIMETROS (INSH) | H6: =IFERROR(__xludf.DUMMYFUNCTION("""COMPUTED_VALUE"""),"INSTALAÇÕES DE MEDIDORES (INSM)") -> INSTALAÇÕES DE MEDIDORES (INSM)
C7: =IFERROR(__xludf.DUMMYFUNCTION("IMPORTRANGE(""https://docs.google.com/spreadsheets/d/1ZMQ1ZJd0nWMp1bKte4MwmpuiYfPuptkAdyS2OLhz2tY/edit?gid=867584558#gid=867584558"",""Itapipoca!B14:G14"")"),6.0) -> 6 | D7: =IFERROR(__xludf.DUMMYFUNCTION("""COMPUTED_VALUE"""),5.0) -> 5 | E7: =IFERROR(__xludf.DUMMYFUNCTION("""COMPUTED_VALUE"""),1.0) -> 1 | F7: =IFERROR(__xludf.DUMMYFUNCTION("""COMPUTED_VALUE"""),3.0) -> 3 | G7: =IFERROR(__xludf.DUMMYFUNCTION("""COMPUTED_VALUE"""),1.0) -> 1 | H7: =IFERROR(__xludf.DUMMYFUNCTION("""COMPUTED_VALUE"""),2.0) -> 2
C8: =SUM(C7:D7) -> 11 | D8: =SUM(E7:F7) -> 4 | E8: =SUM(G7:H7) -> 3 | F8: =IFERROR(__xludf.DUMMYFUNCTION("IMPORTRANGE(""https://docs.google.com/spreadsheets/d/1ZMQ1ZJd0nWMp1bKte4MwmpuiYfPuptkAdyS2OLhz2tY/edit?gid=867584558#gid=867584558"",""Itapipoca!I14"")"),0.11) -> 0.11

Sheet gest
A1: =IFERROR(__xludf.DUMMYFUNCTION("QUERY(IMPORTRANGE(""https://docs.google.com/spreadsheets/d/1sXeXTD5YjBI3DqtVddm1VCMTInMYB4QnHol-BTa5xeo/edit"", ""Programação_Litoral!A:O""), ""SELECT Col4, Col2, Col13"", 1)"),"")
A6: =IFERROR(__xludf.DUMMYFUNCTION("""COMPUTED_VALUE"""),"Atividade") -> Atividade | C6: =IFERROR(__xludf.DUMMYFUNCTION("""COMPUTED_VALUE"""),"Nº de instituições Membros") -> Nº de instituições Membros
A7: =IFERROR(__xludf.DUMMYFUNCTION("""COMPUTED_VALUE"""),"20. Ação de Comunicação / Informação / Capacitação Externa") -> 20. Ação de Comunicação / Informação / Capacitação Externa | B7: =IFERROR(__xludf.DUMMYFUNCTION("""COMPUTED_VALUE"""),44928.0) -> 44928 | C7: =IFERROR(__xludf.DUMMYFUNCTION("""COMPUTED_VALUE"""),"40") -> 40
A8: =IFERROR(__xludf.DUMMYFUNCTION("""COMPUTED_VALUE"""),"20. Ação de Comunicação / Informação / Capacitação Externa") -> 20. Ação de Comunicação / Informação / Capacitação Externa | B8: =IFERROR(__xludf.DUMMYFUNCTION("""COMPUTED_VALUE"""),44928.0) -> 44928
A9: =IFERROR(__xludf.DUMMYFUNCTION("""COMPUTED_VALUE"""),"20. Ação de Comunicação / Informação / Capacitação Externa") -> 20. Ação de Comunicação / Informação / Capacitação Externa
A10: =IFERROR(__xludf.DUMMYFUNCTION("""COMPUTED_VALUE"""),"24. Projetos ou atividades Específicos") -> 24. Projetos ou atividades Específicos | B10: =IFERROR(__xludf.DUMMYFUNCTION("""COMPUTED_VALUE"""),44930.0) -> 44930 | C10: =IFERROR(__xludf.DUMMYFUNCTION("""COMPUTED_VALUE"""),"2") -> 2
A11: =IFERROR(__xludf.DUMMYFUNCTION("""COMPUTED_VALUE"""),"8. CBH – Reunião de Diretoria do CBH") -> 8. CBH – Reunião de Diretoria do CBH | B11: =IFERROR(__xludf.DUMMYFUNCTION("""COMPUTED_VALUE"""),44931.0) -> 44931 | C11: =IFERROR(__xludf.DUMMYFUNCTION("""COMPUTED_VALUE"""),"4") -> 4
A12: =IFERROR(__xludf.DUMMYFUNCTION("""COMPUTED_VALUE"""),"24. Projetos ou atividades Específicos") -> 24. Projetos ou atividades Específicos | B12: =IFERROR(__xludf.DUMMYFUNCTION("""COMPUTED_VALUE"""),44931.0) -> 44931
A13: =IFERROR(__xludf.DUMMYFUNCTION("""COMPUTED_VALUE"""),"24. Projetos ou atividades Específicos") -> 24. Projetos ou atividades Específicos | B13: =IFERROR(__xludf.DUMMYFUNCTION("""COMPUTED_VALUE"""),44934.0) -> 44934
A14: =IFERROR(__xludf.DUMMYFUNCTION("""COMPUTED_VALUE"""),"24. Projetos ou atividades Específicos") -> 24. Projetos ou atividades Específicos | B14: =IFERROR(__xludf.DUMMYFUNCTION("""COMPUTED_VALUE"""),44935.0) -> 44935 | C14: =IFERROR(__xludf.DUMMYFUNCTION("""COMPUTED_VALUE"""),"1") -> 1
A15: =IFERROR(__xludf.DUMMYFUNCTION("""COMPUTED_VALUE"""),"24. Projetos ou atividades Específicos") -> 24. Projetos ou atividades Específicos | B15: =IFERROR(__xludf.DUMMYFUNCTION("""COMPUTED_VALUE"""),44935.0) -> 44935 | C15: =IFERROR(__xludf.DUMMYFUNCTION("""COMPUTED_VALUE"""),"1") -> 1
A16: =IFERROR(__xludf.DUMMYFUNCTION("""COMPUTED_VALUE"""),"9. CBH – Reunião de Câmara Técnica, Câmara específica ou GT") -> 9. CBH – Reunião de Câmara Técnica, Câmara específica ou GT | B16: =IFERROR(__xludf.DUMMYFUNCTION("""COMPUTED_VALUE"""),44936.0) -> 44936 | C16: =IFERROR(__xludf.DUMMYFUNCTION("""COMPUTED_VALUE"""),"4") -> 4
A17: =IFERROR(__xludf.DUMMYFUNCTION("""COMPUTED_VALUE"""),"24. Projetos ou atividades Específicos") -> 24. Projetos ou atividades Específicos | B17: =IFERROR(__xludf.DUMMYFUNCTION("""COMPUTED_VALUE"""),44936.0) -> 44936 | C17: =IFERROR(__xludf.DUMMYFUNCTION("""COMPUTED_VALUE"""),"2") -> 2
A18: =IFERROR(__xludf.DUMMYFUNCTION("""COMPUTED_VALUE"""),"26. Outro") -> 26. Outro | B18: =IFERROR(__xludf.DUMMYFUNCTION("""COMPUTED_VALUE"""),44937.0) -> 44937
A19: =IFERROR(__xludf.DUMMYFUNCTION("""COMPUTED_VALUE"""),"25. Atividade Relacinada a Cobrança/Faturamento") -> 25. Atividade Relacinada a Cobrança/Faturamento | B19: =IFERROR(__xludf.DUMMYFUNCTION("""COMPUTED_VALUE"""),44937.0) -> 44937
A20: =IFERROR(__xludf.DUMMYFUNCTION("""COMPUTED_VALUE"""),"24. Projetos ou atividades Específicos") -> 24. Projetos ou atividades Específicos | B20: =IFERROR(__xludf.DUMMYFUNCTION("""COMPUTED_VALUE"""),44938.0) -> 44938
A21: =IFERROR(__xludf.DUMMYFUNCTION("""COMPUTED_VALUE"""),"24. Projetos ou atividades Específicos") -> 24. Projetos ou atividades Específicos | B21: =IFERROR(__xludf.DUMMYFUNCTION("""COMPUTED_VALUE"""),44942.0) -> 44942
A22: =IFERROR(__xludf.DUMMYFUNCTION("""COMPUTED_VALUE"""),"6. CBH – Reunião Ordinária do Comitê") -> 6. CBH – Reunião Ordinária do Comitê | B22: =IFERROR(__xludf.DUMMYFUNCTION("""COMPUTED_VALUE"""),44942.0) -> 44942
A23: =IFERROR(__xludf.DUMMYFUNCTION("""COMPUTED_VALUE"""),"20. Ação de Comunicação / Informação / Capacitação Externa") -> 20. Ação de Comunicação / Informação / Capacitação Externa | B23: =IFERROR(__xludf.DUMMYFUNCTION("""COMPUTED_VALUE"""),44943.0) -> 44943
A24: =IFERROR(__xludf.DUMMYFUNCTION("""COMPUTED_VALUE"""),"24. Projetos ou atividades Específicos") -> 24. Projetos ou atividades Específicos | B24: =IFERROR(__xludf.DUMMYFUNCTION("""COMPUTED_VALUE"""),44943.0) -> 44943 | C24: =IFERROR(__xludf.DUMMYFUNCTION("""COMPUTED_VALUE"""),"1") -> 1
A25: =IFERROR(__xludf.DUMMYFUNCTION("""COMPUTED_VALUE"""),"24. Projetos ou atividades Específicos") -> 24. Projetos ou atividades Específicos | B25: =IFERROR(__xludf.DUMMYFUNCTION("""COMPUTED_VALUE"""),44944.0) -> 44944
A26: =IFERROR(__xludf.DUMMYFUNCTION("""COMPUTED_VALUE"""),"12. CBH – Reunião do Fórum Cearense de Comitê") -> 12. CBH – Reunião do Fórum Cearense de Comitê | B26: =IFERROR(__xludf.DUMMYFUNCTION("""COMPUTED_VALUE"""),44949.0) -> 44949 | C26: =IFERROR(__xludf.DUMMYFUNCTION("""COMPUTED_VALUE"""),"3") -> 3
A27: =IFERROR(__xludf.DUMMYFUNCTION("""COMPUTED_VALUE"""),"18. Mobilização Social") -> 18. Mobilização Social | B27: =IFERROR(__xludf.DUMMYFUNCTION("""COMPUTED_VALUE"""),44951.0) -> 44951 | C27: =IFERROR(__xludf.DUMMYFUNCTION("""COMPUTED_VALUE"""),"29") -> 29
A28: =IFERROR(__xludf.DUMMYFUNCTION("""COMPUTED_VALUE"""),"Apoio ao Comitê de Bacias") -> Apoio ao Comitê de Bacias | B28: =IFERROR(__xludf.DUMMYFUNCTION("""COMPUTED_VALUE"""),44958.0) -> 44958 | C28: =IFERROR(__xludf.DUMMYFUNCTION("""COMPUTED_VALUE"""),"40") -> 40
A29: =IFERROR(__xludf.DUMMYFUNCTION("""COMPUTED_VALUE"""),"17. CG – Apoio à Formação de CG nos reservatórios (e renovação)") -> 17. CG – Apoio à Formação de CG nos reservatórios (e renovação) | B29: =IFERROR(__xludf.DUMMYFUNCTION("""COMPUTED_VALUE"""),44960.0) -> 44960 | C29: =IFERROR(__xludf.DUMMYFUNCTION("""COMPUTED_VALUE"""),"3") -> 3
A30: =IFERROR(__xludf.DUMMYFUNCTION("""COMPUTED_VALUE"""),"62ª Reunião Ordinária do CBH Litoral") -> 62ª Reunião Ordinária do CBH Litoral | B30: =IFERROR(__xludf.DUMMYFUNCTION("""COMPUTED_VALUE"""),44965.0) -> 44965 | C30: =IFERROR(__xludf.DUMMYFUNCTION("""COMPUTED_VALUE"""),"37") -> 37
A31: =IFERROR(__xludf.DUMMYFUNCTION("""COMPUTED_VALUE"""),"10. CBH – Capacitação do Comitê") -> 10. CBH – Capacitação do Comitê | B31: =IFERROR(__xludf.DUMMYFUNCTION("""COMPUTED_VALUE"""),44965.0) -> 44965 | C31: =IFERROR(__xludf.DUMMYFUNCTION("""COMPUTED_VALUE"""),"37") -> 37
A32: =IFERROR(__xludf.DUMMYFUNCTION("""COMPUTED_VALUE"""),"Apoio ao Comitê") -> Apoio ao Comitê | B32: =IFERROR(__xludf.DUMMYFUNCTION("""COMPUTED_VALUE"""),44966.0) -> 44966
A33: =IFERROR(__xludf.DUMMYFUNCTION("""COMPUTED_VALUE"""),"Apoio ao Comitê") -> Apoio ao Comitê | B33: =IFERROR(__xludf.DUMMYFUNCTION("""COMPUTED_VALUE"""),44966.0) -> 44966
A34: =IFERROR(__xludf.DUMMYFUNCTION("""COMPUTED_VALUE"""),"17. CG – Apoio à Formação de CG nos reservatórios (e renovação)") -> 17. CG – Apoio à Formação de CG nos reservatórios (e renovação) | B34: =IFERROR(__xludf.DUMMYFUNCTION("""COMPUTED_VALUE"""),44971.0) -> 44971 | C34: =IFERROR(__xludf.DUMMYFUNCTION("""COMPUTED_VALUE"""),"2") -> 2
A35: =IFERROR(__xludf.DUMMYFUNCTION("""COMPUTED_VALUE"""),"17. CG – Apoio à Formação de CG nos reservatórios (e renovação)") -> 17. CG – Apoio à Formação de CG nos reservatórios (e renovação) | B35: =IFERROR(__xludf.DUMMYFUNCTION("""COMPUTED_VALUE"""),44972.0) -> 44972
A36: =IFERROR(__xludf.DUMMYFUNCTION("""COMPUTED_VALUE"""),"18. Mobilização Social") -> 18. Mobilização Social | B36: =IFERROR(__xludf.DUMMYFUNCTION("""COMPUTED_VALUE"""),44980.0) -> 44980
A37: =IFERROR(__xludf.DUMMYFUNCTION("""COMPUTED_VALUE"""),"18. Mobilização Social") -> 18. Mobilização Social | B37: =IFERROR(__xludf.DUMMYFUNCTION("""COMPUTED_VALUE"""),44984.0) -> 44984
A38: =IFERROR(__xludf.DUMMYFUNCTION("""COMPUTED_VALUE"""),"17. CG – Apoio à Formação de CG nos reservatórios (e renovação)") -> 17. CG – Apoio à Formação de CG nos reservatórios (e renovação) | B38: =IFERROR(__xludf.DUMMYFUNCTION("""COMPUTED_VALUE"""),44985.0) -> 44985
A39: =IFERROR(__xludf.DUMMYFUNCTION("""COMPUTED_VALUE"""),"20. Ação de Comunicação / Informação / Capacitação Externa") -> 20. Ação de Comunicação / Informação / Capacitação Externa | B39: =IFERROR(__xludf.DUMMYFUNCTION("""COMPUTED_VALUE"""),44986.0) -> 44986 | C39: =IFERROR(__xludf.DUMMYFUNCTION("""COMPUTED_VALUE"""),"40") -> 40
A40: =IFERROR(__xludf.DUMMYFUNCTION("""COMPUTED_VALUE"""),"20. Ação de Comunicação / Informação / Capacitação Externa") -> 20. Ação de Comunicação / Informação / Capacitação Externa | B40: =IFERROR(__xludf.DUMMYFUNCTION("""COMPUTED_VALUE"""),44986.0) -> 44986 | C40: =IFERROR(__xludf.DUMMYFUNCTION("""COMPUTED_VALUE"""),"15") -> 15
A41: =IFERROR(__xludf.DUMMYFUNCTION("""COMPUTED_VALUE"""),"24. Projetos ou atividades Específicos") -> 24. Projetos ou atividades Específicos | B41: =IFERROR(__xludf.DUMMYFUNCTION("""COMPUTED_VALUE"""),44986.0) -> 44986 | C41: =IFERROR(__xludf.DUMMYFUNCTION("""COMPUTED_VALUE"""),"1") -> 1
A42: =IFERROR(__xludf.DUMMYFUNCTION("""COMPUTED_VALUE"""),"18. Mobilização Social") -> 18. Mobilização Social | B42: =IFERROR(__xludf.DUMMYFUNCTION("""COMPUTED_VALUE"""),44986.0) -> 44986 | C42: =IFERROR(__xludf.DUMMYFUNCTION("""COMPUTED_VALUE"""),"40") -> 40
A43: =IFERROR(__xludf.DUMMYFUNCTION("""COMPUTED_VALUE"""),"18. Mobilização Social") -> 18. Mobilização Social | B43: =IFERROR(__xludf.DUMMYFUNCTION("""COMPUTED_VALUE"""),44986.0) -> 44986 | C43: =IFERROR(__xludf.DUMMYFUNCTION("""COMPUTED_VALUE"""),"7") -> 7
A44: =IFERROR(__xludf.DUMMYFUNCTION("""COMPUTED_VALUE"""),"18. Mobilização Social") -> 18. Mobilização Social | B44: =IFERROR(__xludf.DUMMYFUNCTION("""COMPUTED_VALUE"""),44986.0) -> 44986 | C44: =IFERROR(__xludf.DUMMYFUNCTION("""COMPUTED_VALUE"""),"6") -> 6
A45: =IFERROR(__xludf.DUMMYFUNCTION("""COMPUTED_VALUE"""),"20. Ação de Comunicação / Informação / Capacitação Externa") -> 20. Ação de Comunicação / Informação / Capacitação Externa | B45: =IFERROR(__xludf.DUMMYFUNCTION("""COMPUTED_VALUE"""),44986.0) -> 44986 | C45: =IFERROR(__xludf.DUMMYFUNCTION("""COMPUTED_VALUE"""),"5") -> 5
A46: =IFERROR(__xludf.DUMMYFUNCTION("""COMPUTED_VALUE"""),"24. Projetos ou atividades Específicos") -> 24. Projetos ou atividades Específicos | B46: =IFERROR(__xludf.DUMMYFUNCTION("""COMPUTED_VALUE"""),44987.0) -> 44987 | C46: =IFERROR(__xludf.DUMMYFUNCTION("""COMPUTED_VALUE"""),"1") -> 1
A47: =IFERROR(__xludf.DUMMYFUNCTION("""COMPUTED_VALUE"""),"20. Ação de Comunicação / Informação / Capacitação Externa") -> 20. Ação de Comunicação / Informação / Capacitação Externa | B47: =IFERROR(__xludf.DUMMYFUNCTION("""COMPUTED_VALUE"""),44987.0) -> 44987
A48: =IFERROR(__xludf.DUMMYFUNCTION("""COMPUTED_VALUE"""),"20. Ação de Comunicação / Informação / Capacitação Externa") -> 20. Ação de Comunicação / Informação / Capacitação Externa | B48: =IFERROR(__xludf.DUMMYFUNCTION("""COMPUTED_VALUE"""),44987.0) -> 44987
A49: =IFERROR(__xludf.DUMMYFUNCTION("""COMPUTED_VALUE"""),"20. Ação de Comunicação / Informação / Capacitação Externa") -> 20. Ação de Comunicação / Informação / Capacitação Externa | B49: =IFERROR(__xludf.DUMMYFUNCTION("""COMPUTED_VALUE"""),44987.0) -> 44987
A50: =IFERROR(__xludf.DUMMYFUNCTION("""COMPUTED_VALUE"""),"8. CBH – Reunião de Diretoria do CBH") -> 8. CBH – Reunião de Diretoria do CBH | B50: =IFERROR(__xludf.DUMMYFUNCTION("""COMPUTED_VALUE"""),44987.0) -> 44987 | C50: =IFERROR(__xludf.DUMMYFUNCTION("""COMPUTED_VALUE"""),"5") -> 5
A51: =IFERROR(__xludf.DUMMYFUNCTION("""COMPUTED_VALUE"""),"20. Ação de Comunicação / Informação / Capacitação Externa") -> 20. Ação de Comunicação / Informação / Capacitação Externa | B51: =IFERROR(__xludf.DUMMYFUNCTION("""COMPUTED_VALUE"""),44988.0) -> 44988
A52: =IFERROR(__xludf.DUMMYFUNCTION("""COMPUTED_VALUE"""),"20. Ação de Comunicação / Informação / Capacitação Externa") -> 20. Ação de Comunicação / Informação / Capacitação Externa | B52: =IFERROR(__xludf.DUMMYFUNCTION("""COMPUTED_VALUE"""),44991.0) -> 44991
A53: =IFERROR(__xludf.DUMMYFUNCTION("""COMPUTED_VALUE"""),"20. Ação de Comunicação / Informação / Capacitação Externa") -> 20. Ação de Comunicação / Informação / Capacitação Externa | B53: =IFERROR(__xludf.DUMMYFUNCTION("""COMPUTED_VALUE"""),44991.0) -> 44991
A54: =IFERROR(__xludf.DUMMYFUNCTION("""COMPUTED_VALUE"""),"18. Mobilização Social") -> 18. Mobilização Social | B54: =IFERROR(__xludf.DUMMYFUNCTION("""COMPUTED_VALUE"""),44991.0) -> 44991 | C54: =IFERROR(__xludf.DUMMYFUNCTION("""COMPUTED_VALUE"""),"6") -> 6
A55: =IFERROR(__xludf.DUMMYFUNCTION("""COMPUTED_VALUE"""),"20. Ação de Comunicação / Informação / Capacitação Externa") -> 20. Ação de Comunicação / Informação / Capacitação Externa | B55: =IFERROR(__xludf.DUMMYFUNCTION("""COMPUTED_VALUE"""),44991.0) -> 44991
A56: =IFERROR(__xludf.DUMMYFUNCTION("""COMPUTED_VALUE"""),"24. Projetos ou atividades Específicos") -> 24. Projetos ou atividades Específicos | B56: =IFERROR(__xludf.DUMMYFUNCTION("""COMPUTED_VALUE"""),44991.0) -> 44991
A57: =IFERROR(__xludf.DUMMYFUNCTION("""COMPUTED_VALUE"""),"7. CBH – Reunião Extraordinária do Comitê") -> 7. CBH – Reunião Extraordinária do Comitê | B57: =IFERROR(__xludf.DUMMYFUNCTION("""COMPUTED_VALUE"""),44992.0) -> 44992
A58: =IFERROR(__xludf.DUMMYFUNCTION("""COMPUTED_VALUE"""),"7. CBH – Reunião Extraordinária do Comitê") -> 7. CBH – Reunião Extraordinária do Comitê | B58: =IFERROR(__xludf.DUMMYFUNCTION("""COMPUTED_VALUE"""),44993.0) -> 44993 | C58: =IFERROR(__xludf.DUMMYFUNCTION("""COMPUTED_VALUE"""),"31") -> 31
A59: =IFERROR(__xludf.DUMMYFUNCTION("""COMPUTED_VALUE"""),"10. CBH – Capacitação do Comitê") -> 10. CBH – Capacitação do Comitê | B59: =IFERROR(__xludf.DUMMYFUNCTION("""COMPUTED_VALUE"""),44993.0) -> 44993 | C59: =IFERROR(__xludf.DUMMYFUNCTION("""COMPUTED_VALUE"""),"31") -> 31
A60: =IFERROR(__xludf.DUMMYFUNCTION("""COMPUTED_VALUE"""),"7. CBH – Reunião Extraordinária do Comitê") -> 7. CBH – Reunião Extraordinária do Comitê | B60: =IFERROR(__xludf.DUMMYFUNCTION("""COMPUTED_VALUE"""),44993.0) -> 44993
A61: =IFERROR(__xludf.DUMMYFUNCTION("""COMPUTED_VALUE"""),"9. CBH – Reunião de Câmara Técnica, Câmara específica ou GT") -> 9. CBH – Reunião de Câmara Técnica, Câmara específica ou GT | B61: =IFERROR(__xludf.DUMMYFUNCTION("""COMPUTED_VALUE"""),44995.0) -> 44995 | C61: =IFERROR(__xludf.DUMMYFUNCTION("""COMPUTED_VALUE"""),"5") -> 5
A62: =IFERROR(__xludf.DUMMYFUNCTION("""COMPUTED_VALUE"""),"20. Ação de Comunicação / Informação / Capacitação Externa") -> 20. Ação de Comunicação / Informação / Capacitação Externa | B62: =IFERROR(__xludf.DUMMYFUNCTION("""COMPUTED_VALUE"""),44995.0) -> 44995
A63: =IFERROR(__xludf.DUMMYFUNCTION("""COMPUTED_VALUE"""),"24. Projetos ou atividades Específicos") -> 24. Projetos ou atividades Específicos | B63: =IFERROR(__xludf.DUMMYFUNCTION("""COMPUTED_VALUE"""),44995.0) -> 44995
A64: =IFERROR(__xludf.DUMMYFUNCTION("""COMPUTED_VALUE"""),"12. CBH – Reunião do Fórum Cearense de Comitê") -> 12. CBH – Reunião do Fórum Cearense de Comitê | B64: =IFERROR(__xludf.DUMMYFUNCTION("""COMPUTED_VALUE"""),44998.0) -> 44998 | C64: =IFERROR(__xludf.DUMMYFUNCTION("""COMPUTED_VALUE"""),"4") -> 4
A65: =IFERROR(__xludf.DUMMYFUNCTION("""COMPUTED_VALUE"""),"20. Ação de Comunicação / Informação / Capacitação Externa") -> 20. Ação de Comunicação / Informação / Capacitação Externa | B65: =IFERROR(__xludf.DUMMYFUNCTION("""COMPUTED_VALUE"""),44998.0) -> 44998
A66: =IFERROR(__xludf.DUMMYFUNCTION("""COMPUTED_VALUE"""),"24. Projetos ou atividades Específicos") -> 24. Projetos ou atividades Específicos | B66: =IFERROR(__xludf.DUMMYFUNCTION("""COMPUTED_VALUE"""),44999.0) -> 44999
A67: =IFERROR(__xludf.DUMMYFUNCTION("""COMPUTED_VALUE"""),"20. Ação de Comunicação / Informação / Capacitação Externa") -> 20. Ação de Comunicação / Informação / Capacitação Externa | B67: =IFERROR(__xludf.DUMMYFUNCTION("""COMPUTED_VALUE"""),44999.0) -> 44999
A68: =IFERROR(__xludf.DUMMYFUNCTION("""COMPUTED_VALUE"""),"20. Ação de Comunicação / Informação / Capacitação Externa") -> 20. Ação de Comunicação / Informação / Capacitação Externa | B68: =IFERROR(__xludf.DUMMYFUNCTION("""COMPUTED_VALUE"""),45000.0) -> 45000
A69: =IFERROR(__xludf.DUMMYFUNCTION("""COMPUTED_VALUE"""),"24. Projetos ou atividades Específicos") -> 24. Projetos ou atividades Específicos | B69: =IFERROR(__xludf.DUMMYFUNCTION("""COMPUTED_VALUE"""),45000.0) -> 45000
A70: =IFERROR(__xludf.DUMMYFUNCTION("""COMPUTED_VALUE"""),"17. CG – Apoio à Formação de CG nos reservatórios (e renovação)") -> 17. CG – Apoio à Formação de CG nos reservatórios (e renovação) | B70: =IFERROR(__xludf.DUMMYFUNCTION("""COMPUTED_VALUE"""),45001.0) -> 45001
A71: =IFERROR(__xludf.DUMMYFUNCTION("""COMPUTED_VALUE"""),"17. CG – Apoio à Formação de CG nos reservatórios (e renovação)") -> 17. CG – Apoio à Formação de CG nos reservatórios (e renovação) | B71: =IFERROR(__xludf.DUMMYFUNCTION("""COMPUTED_VALUE"""),45002.0) -> 45002
A72: =IFERROR(__xludf.DUMMYFUNCTION("""COMPUTED_VALUE"""),"20. Ação de Comunicação / Informação / Capacitação Externa") -> 20. Ação de Comunicação / Informação / Capacitação Externa | B72: =IFERROR(__xludf.DUMMYFUNCTION("""COMPUTED_VALUE"""),45005.0) -> 45005 | C72: =IFERROR(__xludf.DUMMYFUNCTION("""COMPUTED_VALUE"""),"2") -> 2
A73: =IFERROR(__xludf.DUMMYFUNCTION("""COMPUTED_VALUE"""),"20. Ação de Comunicação / Informação / Capacitação Externa") -> 20. Ação de Comunicação / Informação / Capacitação Externa | B73: =IFERROR(__xludf.DUMMYFUNCTION("""COMPUTED_VALUE"""),45005.0) -> 45005
A74: =IFERROR(__xludf.DUMMYFUNCTION("""COMPUTED_VALUE"""),"20. Ação de Comunicação / Informação / Capacitação Externa") -> 20. Ação de Comunicação / Informação / Capacitação Externa | B74: =IFERROR(__xludf.DUMMYFUNCTION("""COMPUTED_VALUE"""),45006.0) -> 45006
A75: =IFERROR(__xludf.DUMMYFUNCTION("""COMPUTED_VALUE"""),"20. Ação de Comunicação / Informação / Capacitação Externa") -> 20. Ação de Comunicação / Informação / Capacitação Externa | B75: =IFERROR(__xludf.DUMMYFUNCTION("""COMPUTED_VALUE"""),45006.0) -> 45006
A76: =IFERROR(__xludf.DUMMYFUNCTION("""COMPUTED_VALUE"""),"20. Ação de Comunicação / Informação / Capacitação Externa") -> 20. Ação de Comunicação / Informação / Capacitação Externa | B76: =IFERROR(__xludf.DUMMYFUNCTION("""COMPUTED_VALUE"""),45006.0) -> 45006
A77: =IFERROR(__xludf.DUMMYFUNCTION("""COMPUTED_VALUE"""),"20. Ação de Comunicação / Informação / Capacitação Externa") -> 20. Ação de Comunicação / Informação / Capacitação Externa | B77: =IFERROR(__xludf.DUMMYFUNCTION("""COMPUTED_VALUE"""),45008.0) -> 45008 | C77: =IFERROR(__xludf.DUMMYFUNCTION("""COMPUTED_VALUE"""),"1") -> 1
A78: =IFERROR(__xludf.DUMMYFUNCTION("""COMPUTED_VALUE"""),"20. Ação de Comunicação / Informação / Capacitação Externa") -> 20. Ação de Comunicação / Informação / Capacitação Externa | B78: =IFERROR(__xludf.DUMMYFUNCTION("""COMPUTED_VALUE"""),45008.0) -> 45008
A79: =IFERROR(__xludf.DUMMYFUNCTION("""COMPUTED_VALUE"""),"23. Audiência Pública") -> 23. Audiência Pública | B79: =IFERROR(__xludf.DUMMYFUNCTION("""COMPUTED_VALUE"""),45009.0) -> 45009 | C79: =IFERROR(__xludf.DUMMYFUNCTION("""COMPUTED_VALUE"""),"1") -> 1
A80: =IFERROR(__xludf.DUMMYFUNCTION("""COMPUTED_VALUE"""),"24. Projetos ou atividades Específicos") -> 24. Projetos ou atividades Específicos | B80: =IFERROR(__xludf.DUMMYFUNCTION("""COMPUTED_VALUE"""),45009.0) -> 45009
A81: =IFERROR(__xludf.DUMMYFUNCTION("""COMPUTED_VALUE"""),"20. Ação de Comunicação / Informação / Capacitação Externa") -> 20. Ação de Comunicação / Informação / Capacitação Externa | B81: =IFERROR(__xludf.DUMMYFUNCTION("""COMPUTED_VALUE"""),45012.0) -> 45012 | C81: =IFERROR(__xludf.DUMMYFUNCTION("""COMPUTED_VALUE"""),"1") -> 1
A82: =IFERROR(__xludf.DUMMYFUNCTION("""COMPUTED_VALUE"""),"24. Projetos ou atividades Específicos") -> 24. Projetos ou atividades Específicos | B82: =IFERROR(__xludf.DUMMYFUNCTION("""COMPUTED_VALUE"""),45013.0) -> 45013 | C82: =IFERROR(__xludf.DUMMYFUNCTION("""COMPUTED_VALUE"""),"2") -> 2
A83: =IFERROR(__xludf.DUMMYFUNCTION("""COMPUTED_VALUE"""),"24. Projetos ou atividades Específicos") -> 24. Projetos ou atividades Específicos | B83: =IFERROR(__xludf.DUMMYFUNCTION("""COMPUTED_VALUE"""),45014.0) -> 45014 | C83: =IFERROR(__xludf.DUMMYFUNCTION("""COMPUTED_VALUE"""),"1") -> 1
A84: =IFERROR(__xludf.DUMMYFUNCTION("""COMPUTED_VALUE"""),"24. Projetos ou atividades Específicos") -> 24. Projetos ou atividades Específicos | B84: =IFERROR(__xludf.DUMMYFUNCTION("""COMPUTED_VALUE"""),45015.0) -> 45015
A85: =IFERROR(__xludf.DUMMYFUNCTION("""COMPUTED_VALUE"""),"24. Projetos ou atividades Específicos") -> 24. Projetos ou atividades Específicos | B85: =IFERROR(__xludf.DUMMYFUNCTION("""COMPUTED_VALUE"""),45016.0) -> 45016
A86: =IFERROR(__xludf.DUMMYFUNCTION("""COMPUTED_VALUE"""),"18. Mobilização Social") -> 18. Mobilização Social | B86: =IFERROR(__xludf.DUMMYFUNCTION("""COMPUTED_VALUE"""),45019.0) -> 45019 | C86: =IFERROR(__xludf.DUMMYFUNCTION("""COMPUTED_VALUE"""),"4") -> 4
A87: =IFERROR(__xludf.DUMMYFUNCTION("""COMPUTED_VALUE"""),"24. Projetos ou atividades Específicos") -> 24. Projetos ou atividades Específicos | B87: =IFERROR(__xludf.DUMMYFUNCTION("""COMPUTED_VALUE"""),44989.0) -> 44989
A88: =IFERROR(__xludf.DUMMYFUNCTION("""COMPUTED_VALUE"""),"24. Projetos ou atividades Específicos") -> 24. Projetos ou atividades Específicos | B88: =IFERROR(__xludf.DUMMYFUNCTION("""COMPUTED_VALUE"""),45021.0) -> 45021
A89: =IFERROR(__xludf.DUMMYFUNCTION("""COMPUTED_VALUE"""),"20. Ação de Comunicação / Informação / Capacitação Externa") -> 20. Ação de Comunicação / Informação / Capacitação Externa | B89: =IFERROR(__xludf.DUMMYFUNCTION("""COMPUTED_VALUE"""),45026.0) -> 45026
A90: =IFERROR(__xludf.DUMMYFUNCTION("""COMPUTED_VALUE"""),"8. CBH – Reunião de Diretoria do CBH") -> 8. CBH – Reunião de Diretoria do CBH | B90: =IFERROR(__xludf.DUMMYFUNCTION("""COMPUTED_VALUE"""),44996.0) -> 44996 | C90: =IFERROR(__xludf.DUMMYFUNCTION("""COMPUTED_VALUE"""),"4") -> 4
A91: =IFERROR(__xludf.DUMMYFUNCTION("""COMPUTED_VALUE"""),"15. CG – Reunião de Comissão Gestora") -> 15. CG – Reunião de Comissão Gestora | B91: =IFERROR(__xludf.DUMMYFUNCTION("""COMPUTED_VALUE"""),45028.0) -> 45028 | C91: =IFERROR(__xludf.DUMMYFUNCTION("""COMPUTED_VALUE"""),"7") -> 7
A92: =IFERROR(__xludf.DUMMYFUNCTION("""COMPUTED_VALUE"""),"9. CBH – Reunião de Câmara Técnica, Câmara específica ou GT") -> 9. CBH – Reunião de Câmara Técnica, Câmara específica ou GT | B92: =IFERROR(__xludf.DUMMYFUNCTION("""COMPUTED_VALUE"""),45029.0) -> 45029 | C92: =IFERROR(__xludf.DUMMYFUNCTION("""COMPUTED_VALUE"""),"10") -> 10
A93: =IFERROR(__xludf.DUMMYFUNCTION("""COMPUTED_VALUE"""),"24. Projetos ou atividades Específicos") -> 24. Projetos ou atividades Específicos | B93: =IFERROR(__xludf.DUMMYFUNCTION("""COMPUTED_VALUE"""),45030.0) -> 45030 | C93: =IFERROR(__xludf.DUMMYFUNCTION("""COMPUTED_VALUE"""),"3") -> 3
A94: =IFERROR(__xludf.DUMMYFUNCTION("""COMPUTED_VALUE"""),"12. CBH – Reunião do Fórum Cearense de Comitê") -> 12. CBH – Reunião do Fórum Cearense de Comitê | B94: =IFERROR(__xludf.DUMMYFUNCTION("""COMPUTED_VALUE"""),45071.0) -> 45071 | C94: =IFERROR(__xludf.DUMMYFUNCTION("""COMPUTED_VALUE"""),"1") -> 1
A95: =IFERROR(__xludf.DUMMYFUNCTION("""COMPUTED_VALUE"""),"20. Ação de Comunicação / Informação / Capacitação Externa") -> 20. Ação de Comunicação / Informação / Capacitação Externa | B95: =IFERROR(__xludf.DUMMYFUNCTION("""COMPUTED_VALUE"""),45047.0) -> 45047
A96: =IFERROR(__xludf.DUMMYFUNCTION("""COMPUTED_VALUE"""),"17. CG – Apoio à Formação de CG nos reservatórios (e renovação)") -> 17. CG – Apoio à Formação de CG nos reservatórios (e renovação) | B96: =IFERROR(__xludf.DUMMYFUNCTION("""COMPUTED_VALUE"""),45048.0) -> 45048
A97: =IFERROR(__xludf.DUMMYFUNCTION("""COMPUTED_VALUE"""),"20. Ação de Comunicação / Informação / Capacitação Externa") -> 20. Ação de Comunicação / Informação / Capacitação Externa | B97: =IFERROR(__xludf.DUMMYFUNCTION("""COMPUTED_VALUE"""),45048.0) -> 45048
A98: =IFERROR(__xludf.DUMMYFUNCTION("""COMPUTED_VALUE"""),"24. Projetos ou atividades Específicos") -> 24. Projetos ou atividades Específicos | B98: =IFERROR(__xludf.DUMMYFUNCTION("""COMPUTED_VALUE"""),45048.0) -> 45048
A99: =IFERROR(__xludf.DUMMYFUNCTION("""COMPUTED_VALUE"""),"17. CG – Apoio à Formação de CG nos reservatórios (e renovação)") -> 17. CG – Apoio à Formação de CG nos reservatórios (e renovação) | B99: =IFERROR(__xludf.DUMMYFUNCTION("""COMPUTED_VALUE"""),45049.0) -> 45049
A100: =IFERROR(__xludf.DUMMYFUNCTION("""COMPUTED_VALUE"""),"20. Ação de Comunicação / Informação / Capacitação Externa") -> 20. Ação de Comunicação / Informação / Capacitação Externa | B100: =IFERROR(__xludf.DUMMYFUNCTION("""COMPUTED_VALUE"""),45050.0) -> 45050
A101: =IFERROR(__xludf.DUMMYFUNCTION("""COMPUTED_VALUE"""),"20. Ação de Comunicação / Informação / Capacitação Externa") -> 20. Ação de Comunicação / Informação / Capacitação Externa | B101: =IFERROR(__xludf.DUMMYFUNCTION("""COMPUTED_VALUE"""),45051.0) -> 45051
A102: =IFERROR(__xludf.DUMMYFUNCTION("""COMPUTED_VALUE"""),"17. CG – Apoio à Formação de CG nos reservatórios (e renovação)") -> 17. CG – Apoio à Formação de CG nos reservatórios (e renovação) | B102: =IFERROR(__xludf.DUMMYFUNCTION("""COMPUTED_VALUE"""),45051.0) -> 45051
A103: =IFERROR(__xludf.DUMMYFUNCTION("""COMPUTED_VALUE"""),"17. CG – Apoio à Formação de CG nos reservatórios (e renovação)") -> 17. CG – Apoio à Formação de CG nos reservatórios (e renovação) | B103: =IFERROR(__xludf.DUMMYFUNCTION("""COMPUTED_VALUE"""),45054.0) -> 45054
A104: =IFERROR(__xludf.DUMMYFUNCTION("""COMPUTED_VALUE"""),"17. CG – Apoio à Formação de CG nos reservatórios (e renovação)") -> 17. CG – Apoio à Formação de CG nos reservatórios (e renovação) | B104: =IFERROR(__xludf.DUMMYFUNCTION("""COMPUTED_VALUE"""),45056.0) -> 45056
...
